project/m2/rtl/compute_core.sv
// GELU Activation — Pipelined SystemVerilog Implementation
// Optimized for throughput, accurate PWL approximation, and saturation safety.
//
// Data format: 32-bit fixed point, Q16.16 (1 sign, 15 integer, 16 fractional)

module compute_core #(
    parameter int DATA_WIDTH = 32,              // total bit width
    parameter int FRAC_BITS  = 16,              // fractional bits (Q16.16)
    parameter int PIPE_DEPTH = 5                // pipeline stages
)(
    input  logic                        clk,
    input  logic                        rst,
    input  logic                        valid_in,
    input  logic signed [DATA_WIDTH-1:0] x,
    output logic                        valid_out,
    output logic signed [DATA_WIDTH-1:0] out
);

    // -------------------------------------------------------------------------
    // Constants in Q16.16 fixed point
    // -------------------------------------------------------------------------
    localparam signed [DATA_WIDTH-1:0] CONST_1 = 32'sd52261;  // sqrt(2/pi)
    localparam signed [DATA_WIDTH-1:0] CONST_2 = 32'sd2337;   // CONST_1 * 0.044715
    localparam signed [DATA_WIDTH-1:0] ONE     = 32'sd65536;  // 1.0 in Q16.16

    // -------------------------------------------------------------------------
    // Pipeline valid shift register
    // -------------------------------------------------------------------------
    // valid_pipe tracks stages 1 to (PIPE_DEPTH-1). The final stage is valid_out.
    logic [PIPE_DEPTH-2:0] valid_pipe;

    always_ff @(posedge clk) begin
        if (rst) begin
            valid_pipe <= '0;
        end else begin
            valid_pipe <= {valid_pipe[PIPE_DEPTH-3:0], valid_in};
        end
    end

    // -------------------------------------------------------------------------
    // Pipeline Slot 1:
    // -------------------------------------------------------------------------
    logic signed [DATA_WIDTH-1:0] s1_var1, s1_var2, s1_var3, s1_var4;

    // No reset on datapath to save area. Values only matter when valid_pipe[0] is high.
    always_ff @(posedge clk) begin
        s1_var1 <= ($signed(64'(x)) * $signed(64'(x))) >>> FRAC_BITS;
        s1_var2 <= ($signed(64'(CONST_2)) * $signed(64'(x))) >>> FRAC_BITS;
        s1_var3 <= ($signed(64'(CONST_1)) * $signed(64'(x))) >>> FRAC_BITS;
        s1_var4 <= x >>> 1;
    end

    // -------------------------------------------------------------------------
    // Pipeline Slot 2:
    // -------------------------------------------------------------------------
    logic signed [DATA_WIDTH-1:0] s2_var5;
    logic signed [DATA_WIDTH-1:0] s2_var3, s2_var4;

    always_ff @(posedge clk) begin
        s2_var5 <= ($signed(64'(s1_var1)) * $signed(64'(s1_var2))) >>> FRAC_BITS;
        s2_var3 <= s1_var3;
        s2_var4 <= s1_var4;
    end

    // -------------------------------------------------------------------------
    // Pipeline Slot 3:
    // -------------------------------------------------------------------------
    logic signed [DATA_WIDTH-1:0] s3_var6;
    logic signed [DATA_WIDTH-1:0] s3_var4;

    always_ff @(posedge clk) begin
        s3_var6 <= s2_var5 + s2_var3;
        s3_var4 <= s2_var4;
    end

// --- Place these at the top of the module or right before Slot 4 ---
    localparam signed [DATA_WIDTH-1:0] TANH_SAT   = 32'sd65536;   
    localparam signed [DATA_WIDTH-1:0] THRESH_4   = 32'sd262144;  
    localparam signed [DATA_WIDTH-1:0] THRESH_2   = 32'sd131072;  
    localparam signed [DATA_WIDTH-1:0] THRESH_1   = 32'sd65536;   
    localparam signed [DATA_WIDTH-1:0] THRESH_05  = 32'sd32768;   
    localparam signed [DATA_WIDTH-1:0] SLOPE_LIN  = 32'sd65536;   
    localparam signed [DATA_WIDTH-1:0] BASE_2     = 32'sd59330;   
    localparam signed [DATA_WIDTH-1:0] SLOPE_2    = 32'sd1600;    
    localparam signed [DATA_WIDTH-1:0] BASE_1     = 32'sd49933;   
    localparam signed [DATA_WIDTH-1:0] SLOPE_1    = 32'sd9408;    
    localparam signed [DATA_WIDTH-1:0] BASE_05    = 32'sd30284;   
    localparam signed [DATA_WIDTH-1:0] SLOPE_05   = 32'sd39256;   

    // -------------------------------------------------------------------------
    // Pipeline Slot 4: Combinational PWL + Registered Stage
    // -------------------------------------------------------------------------
    logic signed [DATA_WIDTH-1:0] next_pwl; 
    logic signed [DATA_WIDTH-1:0] s4_var7, s4_var4;
    logic signed [DATA_WIDTH-1:0] abs_var6;
    logic                         sign_var6;

    assign abs_var6  = (s3_var6 < 0) ? -s3_var6 : s3_var6;
    assign sign_var6 = s3_var6[DATA_WIDTH-1];

    always_comb begin
        // High-precision Piecewise linear tanh
        if (abs_var6 >= THRESH_4)
            next_pwl = sign_var6 ? -TANH_SAT : TANH_SAT;
        else if (abs_var6 >= THRESH_2) begin
            // Calculate the segment offset first
            next_pwl = (64'(SLOPE_2) * (abs_var6 - THRESH_2)) >>> FRAC_BITS;
            // Add to base then apply sign
            next_pwl = sign_var6 ? -(BASE_2 + next_pwl) : (BASE_2 + next_pwl);
        end else if (abs_var6 >= THRESH_1) begin
            next_pwl = (64'(SLOPE_1) * (abs_var6 - THRESH_1)) >>> FRAC_BITS;
            next_pwl = sign_var6 ? -(BASE_1 + next_pwl) : (BASE_1 + next_pwl);
        end else if (abs_var6 >= THRESH_05) begin
            next_pwl = (64'(SLOPE_05) * (abs_var6 - THRESH_05)) >>> FRAC_BITS;
            next_pwl = sign_var6 ? -(BASE_05 + next_pwl) : (BASE_05 + next_pwl);
        end else begin
            // Use the original signed value for the linear region to ensure a smooth zero-crossing
            next_pwl = (64'(SLOPE_LIN) * s3_var6) >>> FRAC_BITS;
        end
    end

    always_ff @(posedge clk) begin
        s4_var7 <= ONE + next_pwl;  
        s4_var4 <= s3_var4;
    end
    // -------------------------------------------------------------------------
    // Pipeline Slot 5: Output with Saturation
    // -------------------------------------------------------------------------
    logic signed [63:0] out_full;
    assign out_full = ($signed(64'(s4_var7)) * $signed(64'(s4_var4))) >>> FRAC_BITS;

    always_ff @(posedge clk) begin
        if (rst) begin
            valid_out <= 1'b0;
            out       <= '0;
        end else begin
            valid_out <= valid_pipe[PIPE_DEPTH-2]; // Synced strictly with final data
            
            // Saturation limit clamping
            if (out_full > 64'sd2147483647)
                out <= 32'sd2147483647;
            else if (out_full < -64'sd2147483648)
                out <= -32'sd2147483648;
            else
                out <= out_full[31:0];
        end
    end
    
    // -------------------------------------------------------------------------
    // Simulation hooks
    // -------------------------------------------------------------------------
    initial begin
        $dumpfile("dump.vcd"); 
        $dumpvars(0, compute_core);     
    end

endmodule

project/m2/sim/compute_core_run.vcd
$date
	Sun May  3 00:32:52 2026
$end
$version
	Icarus Verilog
$end
$timescale
	1ps
$end
$scope module compute_core $end
$var wire 1 ! clk $end
$var wire 1 " rst $end
$var wire 1 # valid_in $end
$var wire 32 $ x [31:0] $end
$var wire 1 % sign_var6 $end
$var wire 64 & out_full [63:0] $end
$var wire 32 ' abs_var6 [31:0] $end
$var parameter 32 ( BASE_05 $end
$var parameter 32 ) BASE_1 $end
$var parameter 32 * BASE_2 $end
$var parameter 32 + CONST_1 $end
$var parameter 32 , CONST_2 $end
$var parameter 32 - DATA_WIDTH $end
$var parameter 32 . FRAC_BITS $end
$var parameter 32 / ONE $end
$var parameter 32 0 PIPE_DEPTH $end
$var parameter 32 1 SLOPE_05 $end
$var parameter 32 2 SLOPE_1 $end
$var parameter 32 3 SLOPE_2 $end
$var parameter 32 4 SLOPE_LIN $end
$var parameter 32 5 TANH_SAT $end
$var parameter 32 6 THRESH_05 $end
$var parameter 32 7 THRESH_1 $end
$var parameter 32 8 THRESH_2 $end
$var parameter 32 9 THRESH_4 $end
$var reg 32 : next_pwl [31:0] $end
$var reg 32 ; out [31:0] $end
$var reg 32 < s1_var1 [31:0] $end
$var reg 32 = s1_var2 [31:0] $end
$var reg 32 > s1_var3 [31:0] $end
$var reg 32 ? s1_var4 [31:0] $end
$var reg 32 @ s2_var3 [31:0] $end
$var reg 32 A s2_var4 [31:0] $end
$var reg 32 B s2_var5 [31:0] $end
$var reg 32 C s3_var4 [31:0] $end
$var reg 32 D s3_var6 [31:0] $end
$var reg 32 E s4_var4 [31:0] $end
$var reg 32 F s4_var7 [31:0] $end
$var reg 1 G valid_out $end
$var reg 4 H valid_pipe [3:0] $end
$upscope $end
$enddefinitions $end
$comment Show the parameter values. $end
$dumpall
b1000000000000000000 9
b100000000000000000 8
b10000000000000000 7
b1000000000000000 6
b10000000000000000 5
b10000000000000000 4
b11001000000 3
b10010011000000 2
b1001100101011000 1
b101 0
b10000000000000000 /
b10000 .
b100000 -
b100100100001 ,
b1100110000100101 +
b1110011111000010 *
b1100001100001101 )
b111011001001100 (
$end
#0
$dumpvars
b0 H
0G
bx F
bx E
bx D
bx C
bx B
bx A
bx @
b0 ?
b0 >
b0 =
b0 <
b0 ;
bx :
bx '
bx &
x%
b0 $
0#
1"
1!
$end
#5000
0!
#10000
1#
0"
b0 A
b0 @
b0 B
1!
#15000
0!
#20000
b0 :
b0 '
0%
b1 H
b0 C
b0 D
bx ;
1!
#25000
0!
#30000
b0 &
b0 E
b10000000000000000 F
b11 H
1!
#35000
0!
#40000
b111 H
b0 ;
1!
#45000
0!
#50000
b1111 H
1!
#55000
0!
#60000
0#
1G
1!
#65000
0!
#70000
b10000000000000000 $
1#
b1110 H
1!
#75000
0!
#80000
b1101 H
b1000000000000000 ?
b1100110000100101 >
b100100100001 =
b10000000000000000 <
1!
#85000
0!
#90000
b1000000000000000 A
b1100110000100101 @
b100100100001 B
b1011 H
1!
#95000
0!
#100000
b1010100101100000 :
b1101010101000110 '
b111 H
b1000000000000000 C
b1101010101000110 D
1!
#105000
0!
#110000
b1101010010110000 &
0G
b1000000000000000 E
b11010100101100000 F
b1111 H
1!
#115000
0!
#120000
0#
b1101010010110000 ;
1G
1!
#125000
0!
#130000
b11111111111111110000000000000000 $
1#
b1110 H
1!
#135000
0!
#140000
b1101 H
b11111111111111111000000000000000 ?
b11111111111111110011001111011011 >
b11111111111111111111011011011111 =
1!
#145000
0!
#150000
b11111111111111111000000000000000 A
b11111111111111110011001111011011 @
b11111111111111111111011011011111 B
b1011 H
1!
#155000
0!
#160000
b11111111111111110101011010100000 :
1%
b111 H
b11111111111111111000000000000000 C
b11111111111111110010101010111010 D
1!
#165000
0!
#170000
b1111111111111111111111111111111111111111111111111101010010110000 &
0G
b11111111111111111000000000000000 E
b101011010100000 F
b1111 H
1!
#175000
0!
#180000
0#
b11111111111111111101010010110000 ;
1G
1!
#185000
0!
#190000
b1110 H
1!
#190001
b0 $
1"
#195001
0!
#200001
b0 H
b0 ?
b0 >
b0 =
b0 <
b0 ;
0G
1!
#205001
0!
#210001
b1010000000000000000 $
1#
0"
b0 A
b0 @
b0 B
1!
#215001
0!
#220001
b0 :
b0 '
0%
b1 H
b101000000000000000 ?
b111111110010111001 >
b10110110100101 =
b110010000000000000000 <
b0 C
b0 D
b11111111111111111101010010110000 ;
1!
#225001
0!
#230001
b0 &
b0 E
b10000000000000000 F
b101000000000000000 A
b111111110010111001 @
b1000111010100011101 B
b11 H
1!
#235001
0!
#240001
b10000000000000000 :
b10000111000111010110 '
b111 H
b101000000000000000 C
b10000111000111010110 D
b0 ;
1!
#245001
0!
#250001
b1010000000000000000 &
b101000000000000000 E
b100000000000000000 F
b1111 H
1!
#255001
0!
#260001
0#
b1010000000000000000 ;
1G
1!
#265001
0!
#270001
b10000000000000000000 $
1#
b1110 H
1!
#275001
0!
#280001
b1101 H
b1000000000000000000 ?
b1100110000100101000 >
b100100100001000 =
b10000000000000000000000 <
1!
#285001
0!
#290001
b1000000000000000000 A
b1100110000100101000 @
b100100100001000000000 B
b1011 H
1!
#295001
0!
#300001
b110001010001100101000 '
b111 H
b1000000000000000000 C
b110001010001100101000 D
1!
#305001
0!
#310001
b10000000000000000000 &
0G
b1000000000000000000 E
b1111 H
1!
#315001
0!
#320001
0#
b10000000000000000000 ;
1G
1!
#325001
0!
#330001
b11111111111110110000000000000000 $
1#
b1110 H
1!
#335001
0!
#340001
b1101 H
b11111111111111011000000000000000 ?
b11111111111111000000001101000111 >
b11111111111111111101001001011011 =
b110010000000000000000 <
1!
#345001
0!
#350001
b11111111111111011000000000000000 A
b11111111111111000000001101000111 @
b11111111111110111000101011100011 B
b1011 H
1!
#355001
0!
#360001
b11111111111111110000000000000000 :
b10000111000111010110 '
1%
b111 H
b11111111111111011000000000000000 C
b11111111111101111000111000101010 D
1!
#365001
0!
#370001
b0 &
0G
b11111111111111011000000000000000 E
b0 F
b1111 H
1!
#375001
0!
#380001
0#
b0 ;
1G
1!
#385001
0!
#390001
b11111111111110000000000000000000 $
1#
b1110 H
1!
#395001
0!
#400001
b1101 H
b11111111111111000000000000000000 ?
b11111111111110011001111011011000 >
b11111111111111111011011011111000 =
b10000000000000000000000 <
1!
#405001
0!
#410001
b11111111111111000000000000000000 A
b11111111111110011001111011011000 @
b11111111111011011011111000000000 B
b1011 H
1!
#415001
0!
#420001
b110001010001100101000 '
b111 H
b11111111111111000000000000000000 C
b11111111111001110101110011011000 D
1!
#425001
0!
#430001
0G
b11111111111111000000000000000000 E
b1111 H
1!
#435001
0!
#440001
0#
1G
1!
#445001
0!
#450001
b1110 H
1!
#450002
b0 $
1"
#455002
0!
#460002
b0 H
b0 ?
b0 >
b0 =
b0 <
0G
1!
#465002
0!
#470002
b10000000000000000 $
1#
0"
b0 A
b0 @
b0 B
1!
#475002
0!
#480002
0#
b0 :
b0 '
0%
b1 H
b1000000000000000 ?
b1100110000100101 >
b100100100001 =
b10000000000000000 <
b0 C
b0 D
1!
#485002
0!
#490002
b0 E
b10000000000000000 F
b1000000000000000 A
b1100110000100101 @
b100100100001 B
b10 H
1!
#495002
0!
#500002
b1010100101100000 :
b1101010101000110 '
b100 H
b1000000000000000 C
b1101010101000110 D
1!
#505002
0!
#510002
b1101010010110000 &
b1000000000000000 E
b11010100101100000 F
b1000 H
1!
#515002
0!
#520002
b0 H
b1101010010110000 ;
1G
1!
#525002
0!
#530002
0G
1!
#530003
b0 $
1"
#535003
0!
#540003
b0 ?
b0 >
b0 =
b0 <
b0 ;
1!
#545003
0!
#550003
1#
0"
b0 A
b0 @
b0 B
1!
#555003
0!
#560003
b0 :
b0 '
b1 H
b0 C
b0 D
b1101010010110000 ;
1!
#565003
0!
#570003
b0 &
b0 E
b10000000000000000 F
b11 H
1!
#575003
0!
#580003
b111 H
b0 ;
1!
#585003
0!
#590003
b1111 H
1!
#595003
0!
#600003
0#
1G
1!
#605003
0!
#610003
b1110 H
1!
#610004
1"
#615004
0!
#620004
b0 H
0G
1!
#625004
0!
#630004
b1000000000000000 $
1#
0"
1!
#635004
0!
#640004
b10000000000000000 $
b1 H
b100000000000000 ?
b110011000010010 >
b10010010000 =
b100000000000000 <
1!
#645004
0!
#650004
b11000000000000000 $
b100000000000000 A
b110011000010010 @
b100100100 B
b1000000000000000 ?
b1100110000100101 >
b100100100001 =
b10000000000000000 <
b11 H
1!
#655004
0!
#660004
b100000000000000000 $
b110011100110110 :
b110011100110110 '
b111 H
b1100000000000000 ?
b10011001000110111 >
b110110110001 =
b100100000000000000 <
b1000000000000000 A
b1100110000100101 @
b100100100001 B
b100000000000000 C
b110011100110110 D
1!
#665004
0!
#670004
b11111111111111111000000000000000 $
b101100111001101 &
b1010100101100000 :
b1101010101000110 '
b100000000000000 E
b10110011100110110 F
b1000000000000000 C
b1101010101000110 D
b1100000000000000 A
b10011001000110111 @
b1111011001110 B
b10000000000000000 ?
b11001100001001010 >
b1001001000010 =
b1000000000000000000 <
b1111 H
1!
#675004
0!
#680004
b11111111111111110000000000000000 $
b1100111010101110 :
b10101000100000101 '
b1101010010110000 &
b11111111111111111100000000000000 ?
b11111111111111111001100111101101 >
b11111111111111111111101101101111 =
b100000000000000 <
b10000000000000000 A
b11001100001001010 @
b100100100001000 B
b1100000000000000 C
b10101000100000101 D
b1000000000000000 E
b11010100101100000 F
b101100111001101 ;
1G
1!
#685004
0!
#690004
b11111111111111101000000000000000 $
b10101101100000010 &
b1110001101100101 :
b11110000101010010 '
b1101010010110000 ;
b1100000000000000 E
b11100111010101110 F
b10000000000000000 C
b11110000101010010 D
b11111111111111111100000000000000 A
b11111111111111111001100111101101 @
b11111111111111111111111011011011 B
b11111111111111111000000000000000 ?
b11111111111111110011001111011011 >
b11111111111111111111011011011111 =
b10000000000000000 <
1!
#695004
0!
#700004
b11111111111111100000000000000000 $
b11111111111111111001100011001000 :
b110011100111000 '
1%
b11110001101100101 &
b11111111111111110100000000000000 ?
b11111111111111101100110111001000 >
b11111111111111111111001001001110 =
b100100000000000000 <
b11111111111111111000000000000000 A
b11111111111111110011001111011011 @
b11111111111111111111011011011111 B
b11111111111111111100000000000000 C
b11111111111111111001100011001000 D
b10000000000000000 E
b11110001101100101 F
b10101101100000010 ;
1!
#705004
0!
#710004
0#
b1111111111111111111111111111111111111111111111111101100111001110 &
b11111111111111110101011010100000 :
b1101010101000110 '
b11110001101100101 ;
b11111111111111111100000000000000 E
b1001100011001000 F
b11111111111111111000000000000000 C
b11111111111111110010101010111010 D
b11111111111111110100000000000000 A
b11111111111111101100110111001000 @
b11111111111111111110000100101111 B
b11111111111111110000000000000000 ?
b11111111111111100110011110110110 >
b11111111111111111110110110111110 =
b1000000000000000000 <
1!
#715004
0!
#720004
b11111111111111110011000101010001 :
b10101000100001001 '
b1111111111111111111111111111111111111111111111111101010010110000 &
b1110 H
b11111111111111110000000000000000 A
b11111111111111100110011110110110 @
b11111111111111111011011011111000 B
b11111111111111110100000000000000 C
b11111111111111101010111011110111 D
b11111111111111111000000000000000 E
b101011010100000 F
b11111111111111111101100111001110 ;
1!
#725004
0!
#730004
b1111111111111111111111111111111111111111111111111101101100000011 &
b11111111111111110001110010011011 :
b11110000101010010 '
b11111111111111111101010010110000 ;
b11111111111111110100000000000000 E
b11000101010001 F
b11111111111111110000000000000000 C
b11111111111111100001111010101110 D
b1100 H
1!
#735004
0!
#740004
b1111111111111111111111111111111111111111111111111110001101100101 &
b1000 H
b11111111111111110000000000000000 E
b1110010011011 F
b11111111111111111101101100000011 ;
1!
#745004
0!
#750004
b11111111111111111110001101100101 ;
b0 H
1!
#755004
0!
#760004
0G
1!
