project/m2/rtl/compute_core.sv
// =========================================================================
// Module:  compute_core
// Project: GELU Activation Kernel — ECE 410/510, M2
// Author:  Created with Cursor — Manager (Claude Opus 4.6)
// Created: 2026-05-03
// Modified: 2026-05-03
//
// Description:
//   Pipelined GELU activation function in synthesizable SystemVerilog.
//   Implements GELU(x) = 0.5 * x * (1 + tanh(c1*x + c2*x^3))
//   using a 10-segment piecewise-linear (PWL) tanh approximation.
//
// Data Format:
//   32-bit signed fixed point, Q16.16 (1 sign, 15 integer, 16 fractional)
//
// Clock Domain:
//   Single clock domain (clk). All sequential logic on posedge clk.
//
// Reset:
//   Synchronous, active-high (rst). Clears valid pipeline and output.
//   Datapath registers are not reset (values gated by valid).
//
// Pipeline:
//   5 stages, 5-cycle latency. Accepts one input per clock when valid_in
//   is asserted. Fully pipelined — no stalls or backpressure.
//
// Port Descriptions:
//   clk       — input,  1-bit        : System clock
//   rst       — input,  1-bit        : Synchronous active-high reset
//   valid_in  — input,  1-bit        : Input data valid strobe
//   x         — input,  [31:0] signed: Input operand in Q16.16
//   valid_out — output, 1-bit        : Output data valid strobe
//   out       — output, [31:0] signed: GELU(x) result in Q16.16
// =========================================================================

module compute_core #(
    parameter int DATA_WIDTH = 32,              // total bit width
    parameter int FRAC_BITS  = 16,              // fractional bits (Q16.16)
    parameter int PIPE_DEPTH = 5                // pipeline stages
)(
    input  logic                        clk,
    input  logic                        rst,
    input  logic                        valid_in,
    input  logic signed [DATA_WIDTH-1:0] x,
    output logic                        valid_out,
    output logic signed [DATA_WIDTH-1:0] out
);

    // -------------------------------------------------------------------------
    // Constants in Q16.16 fixed point
    // -------------------------------------------------------------------------
    localparam signed [DATA_WIDTH-1:0] CONST_1 = 32'sd52261;  // sqrt(2/pi)
    localparam signed [DATA_WIDTH-1:0] CONST_2 = 32'sd2337;   // CONST_1 * 0.044715
    localparam signed [DATA_WIDTH-1:0] ONE     = 32'sd65536;  // 1.0 in Q16.16

    // -------------------------------------------------------------------------
    // Pipeline valid shift register
    // -------------------------------------------------------------------------
    // valid_pipe tracks stages 1 to (PIPE_DEPTH-1). The final stage is valid_out.
    logic [PIPE_DEPTH-2:0] valid_pipe;

    always_ff @(posedge clk) begin
        if (rst) begin
            valid_pipe <= '0;
        end else begin
            valid_pipe <= {valid_pipe[PIPE_DEPTH-3:0], valid_in};
        end
    end

    // -------------------------------------------------------------------------
    // Pipeline Slot 1:
    // -------------------------------------------------------------------------
    logic signed [DATA_WIDTH-1:0] s1_var1, s1_var2, s1_var3, s1_var4;

    // No reset on datapath to save area. Values only matter when valid_pipe[0] is high.
    always_ff @(posedge clk) begin
        s1_var1 <= ($signed(64'(x)) * $signed(64'(x))) >>> FRAC_BITS;
        s1_var2 <= ($signed(64'(CONST_2)) * $signed(64'(x))) >>> FRAC_BITS;
        s1_var3 <= ($signed(64'(CONST_1)) * $signed(64'(x))) >>> FRAC_BITS;
        s1_var4 <= x >>> 1;
    end

    // -------------------------------------------------------------------------
    // Pipeline Slot 2:
    // -------------------------------------------------------------------------
    logic signed [DATA_WIDTH-1:0] s2_var5;
    logic signed [DATA_WIDTH-1:0] s2_var3, s2_var4;

    always_ff @(posedge clk) begin
        s2_var5 <= ($signed(64'(s1_var1)) * $signed(64'(s1_var2))) >>> FRAC_BITS;
        s2_var3 <= s1_var3;
        s2_var4 <= s1_var4;
    end

    // -------------------------------------------------------------------------
    // Pipeline Slot 3:
    // -------------------------------------------------------------------------
    logic signed [DATA_WIDTH-1:0] s3_var6;
    logic signed [DATA_WIDTH-1:0] s3_var4;

    always_ff @(posedge clk) begin
        s3_var6 <= s2_var5 + s2_var3;
        s3_var4 <= s2_var4;
    end

    // PWL Tanh — 10-segment approximation with endpoint-to-endpoint slopes
    // Thresholds (Q16.16)
    localparam signed [DATA_WIDTH-1:0] TANH_SAT    = 32'sd65536;   // 1.0
    localparam signed [DATA_WIDTH-1:0] THRESH_4    = 32'sd262144;  // 4.0
    localparam signed [DATA_WIDTH-1:0] THRESH_3    = 32'sd196608;  // 3.0
    localparam signed [DATA_WIDTH-1:0] THRESH_2    = 32'sd131072;  // 2.0
    localparam signed [DATA_WIDTH-1:0] THRESH_175  = 32'sd114688;  // 1.75
    localparam signed [DATA_WIDTH-1:0] THRESH_15   = 32'sd98304;   // 1.5
    localparam signed [DATA_WIDTH-1:0] THRESH_125  = 32'sd81920;   // 1.25
    localparam signed [DATA_WIDTH-1:0] THRESH_1    = 32'sd65536;   // 1.0
    localparam signed [DATA_WIDTH-1:0] THRESH_075  = 32'sd49152;   // 0.75
    localparam signed [DATA_WIDTH-1:0] THRESH_05   = 32'sd32768;   // 0.5
    // Bases — tanh(threshold) in Q16.16
    localparam signed [DATA_WIDTH-1:0] BASE_3      = 32'sd65212;   // tanh(3.0)
    localparam signed [DATA_WIDTH-1:0] BASE_2      = 32'sd63179;   // tanh(2.0)
    localparam signed [DATA_WIDTH-1:0] BASE_175    = 32'sd61694;   // tanh(1.75)
    localparam signed [DATA_WIDTH-1:0] BASE_15     = 32'sd59320;   // tanh(1.5)
    localparam signed [DATA_WIDTH-1:0] BASE_125    = 32'sd55593;   // tanh(1.25)
    localparam signed [DATA_WIDTH-1:0] BASE_1      = 32'sd49912;   // tanh(1.0)
    localparam signed [DATA_WIDTH-1:0] BASE_075    = 32'sd41625;   // tanh(0.75)
    localparam signed [DATA_WIDTH-1:0] BASE_05     = 32'sd30285;   // tanh(0.5)
    // Slopes — (tanh(upper) - tanh(lower)) / (upper - lower) in Q16.16
    localparam signed [DATA_WIDTH-1:0] SLOPE_3_4   = 32'sd280;     // [3.0, 4.0)
    localparam signed [DATA_WIDTH-1:0] SLOPE_2_3   = 32'sd2033;    // [2.0, 3.0)
    localparam signed [DATA_WIDTH-1:0] SLOPE_175_2 = 32'sd5938;    // [1.75, 2.0)
    localparam signed [DATA_WIDTH-1:0] SLOPE_15_175= 32'sd9497;    // [1.5, 1.75)
    localparam signed [DATA_WIDTH-1:0] SLOPE_125_15= 32'sd14907;   // [1.25, 1.5)
    localparam signed [DATA_WIDTH-1:0] SLOPE_1_125 = 32'sd22725;   // [1.0, 1.25)
    localparam signed [DATA_WIDTH-1:0] SLOPE_075_1 = 32'sd33147;   // [0.75, 1.0)
    localparam signed [DATA_WIDTH-1:0] SLOPE_05_075= 32'sd45359;   // [0.5, 0.75)
    localparam signed [DATA_WIDTH-1:0] SLOPE_LIN   = 32'sd65536;   // [0, 0.5) tanh≈x   

    // -------------------------------------------------------------------------
    // Pipeline Slot 4: Combinational PWL + Registered Stage
    // -------------------------------------------------------------------------
    logic signed [DATA_WIDTH-1:0] next_pwl; 
    logic signed [DATA_WIDTH-1:0] s4_var7, s4_var4;
    logic signed [DATA_WIDTH-1:0] abs_var6;
    logic                         sign_var6;

    assign abs_var6  = (s3_var6 < 0) ? -s3_var6 : s3_var6;
    assign sign_var6 = s3_var6[DATA_WIDTH-1];

    always_comb begin
        if (abs_var6 >= THRESH_4)
            next_pwl = sign_var6 ? -TANH_SAT : TANH_SAT;
        else if (abs_var6 >= THRESH_3) begin
            next_pwl = (64'(SLOPE_3_4) * (abs_var6 - THRESH_3)) >>> FRAC_BITS;
            next_pwl = sign_var6 ? -(BASE_3 + next_pwl) : (BASE_3 + next_pwl);
        end else if (abs_var6 >= THRESH_2) begin
            next_pwl = (64'(SLOPE_2_3) * (abs_var6 - THRESH_2)) >>> FRAC_BITS;
            next_pwl = sign_var6 ? -(BASE_2 + next_pwl) : (BASE_2 + next_pwl);
        end else if (abs_var6 >= THRESH_175) begin
            next_pwl = (64'(SLOPE_175_2) * (abs_var6 - THRESH_175)) >>> FRAC_BITS;
            next_pwl = sign_var6 ? -(BASE_175 + next_pwl) : (BASE_175 + next_pwl);
        end else if (abs_var6 >= THRESH_15) begin
            next_pwl = (64'(SLOPE_15_175) * (abs_var6 - THRESH_15)) >>> FRAC_BITS;
            next_pwl = sign_var6 ? -(BASE_15 + next_pwl) : (BASE_15 + next_pwl);
        end else if (abs_var6 >= THRESH_125) begin
            next_pwl = (64'(SLOPE_125_15) * (abs_var6 - THRESH_125)) >>> FRAC_BITS;
            next_pwl = sign_var6 ? -(BASE_125 + next_pwl) : (BASE_125 + next_pwl);
        end else if (abs_var6 >= THRESH_1) begin
            next_pwl = (64'(SLOPE_1_125) * (abs_var6 - THRESH_1)) >>> FRAC_BITS;
            next_pwl = sign_var6 ? -(BASE_1 + next_pwl) : (BASE_1 + next_pwl);
        end else if (abs_var6 >= THRESH_075) begin
            next_pwl = (64'(SLOPE_075_1) * (abs_var6 - THRESH_075)) >>> FRAC_BITS;
            next_pwl = sign_var6 ? -(BASE_075 + next_pwl) : (BASE_075 + next_pwl);
        end else if (abs_var6 >= THRESH_05) begin
            next_pwl = (64'(SLOPE_05_075) * (abs_var6 - THRESH_05)) >>> FRAC_BITS;
            next_pwl = sign_var6 ? -(BASE_05 + next_pwl) : (BASE_05 + next_pwl);
        end else begin
            next_pwl = (64'(SLOPE_LIN) * s3_var6) >>> FRAC_BITS;
        end
    end

    always_ff @(posedge clk) begin
        s4_var7 <= ONE + next_pwl;  
        s4_var4 <= s3_var4;
    end
    // -------------------------------------------------------------------------
    // Pipeline Slot 5: Output with Saturation
    // -------------------------------------------------------------------------
    logic signed [63:0] out_full;
    assign out_full = ($signed(64'(s4_var7)) * $signed(64'(s4_var4))) >>> FRAC_BITS;

    always_ff @(posedge clk) begin
        if (rst) begin
            valid_out <= 1'b0;
            out       <= '0;
        end else begin
            valid_out <= valid_pipe[PIPE_DEPTH-2]; // Synced strictly with final data
            
            // Saturation limit clamping
            if (out_full > 64'sd2147483647)
                out <= 32'sd2147483647;
            else if (out_full < -64'sd2147483648)
                out <= -32'sd2147483648;
            else
                out <= out_full[31:0];
        end
    end
    
    // -------------------------------------------------------------------------
    // Simulation hooks
    // -------------------------------------------------------------------------
    initial begin
        $dumpfile("dump.vcd"); 
        $dumpvars(0, compute_core);     
    end

endmodule

project/m2/sim/compute_core_run.vcd
$date
	Sun May  3 03:19:59 2026
$end
$version
	Icarus Verilog
$end
$timescale
	1ps
$end
$scope module compute_core $end
$var wire 1 ! clk $end
$var wire 1 " rst $end
$var wire 1 # valid_in $end
$var wire 32 $ x [31:0] $end
$var wire 1 % sign_var6 $end
$var wire 64 & out_full [63:0] $end
$var wire 32 ' abs_var6 [31:0] $end
$var parameter 32 ( BASE_05 $end
$var parameter 32 ) BASE_075 $end
$var parameter 32 * BASE_1 $end
$var parameter 32 + BASE_125 $end
$var parameter 32 , BASE_15 $end
$var parameter 32 - BASE_175 $end
$var parameter 32 . BASE_2 $end
$var parameter 32 / BASE_3 $end
$var parameter 32 0 CONST_1 $end
$var parameter 32 1 CONST_2 $end
$var parameter 32 2 DATA_WIDTH $end
$var parameter 32 3 FRAC_BITS $end
$var parameter 32 4 ONE $end
$var parameter 32 5 PIPE_DEPTH $end
$var parameter 32 6 SLOPE_05_075 $end
$var parameter 32 7 SLOPE_075_1 $end
$var parameter 32 8 SLOPE_125_15 $end
$var parameter 32 9 SLOPE_15_175 $end
$var parameter 32 : SLOPE_175_2 $end
$var parameter 32 ; SLOPE_1_125 $end
$var parameter 32 < SLOPE_2_3 $end
$var parameter 32 = SLOPE_3_4 $end
$var parameter 32 > SLOPE_LIN $end
$var parameter 32 ? TANH_SAT $end
$var parameter 32 @ THRESH_05 $end
$var parameter 32 A THRESH_075 $end
$var parameter 32 B THRESH_1 $end
$var parameter 32 C THRESH_125 $end
$var parameter 32 D THRESH_15 $end
$var parameter 32 E THRESH_175 $end
$var parameter 32 F THRESH_2 $end
$var parameter 32 G THRESH_3 $end
$var parameter 32 H THRESH_4 $end
$var reg 32 I next_pwl [31:0] $end
$var reg 32 J out [31:0] $end
$var reg 32 K s1_var1 [31:0] $end
$var reg 32 L s1_var2 [31:0] $end
$var reg 32 M s1_var3 [31:0] $end
$var reg 32 N s1_var4 [31:0] $end
$var reg 32 O s2_var3 [31:0] $end
$var reg 32 P s2_var4 [31:0] $end
$var reg 32 Q s2_var5 [31:0] $end
$var reg 32 R s3_var4 [31:0] $end
$var reg 32 S s3_var6 [31:0] $end
$var reg 32 T s4_var4 [31:0] $end
$var reg 32 U s4_var7 [31:0] $end
$var reg 1 V valid_out $end
$var reg 4 W valid_pipe [3:0] $end
$upscope $end
$enddefinitions $end
$comment Show the parameter values. $end
$dumpall
b1000000000000000000 H
b110000000000000000 G
b100000000000000000 F
b11100000000000000 E
b11000000000000000 D
b10100000000000000 C
b10000000000000000 B
b1100000000000000 A
b1000000000000000 @
b10000000000000000 ?
b10000000000000000 >
b100011000 =
b11111110001 <
b101100011000101 ;
b1011100110010 :
b10010100011001 9
b11101000111011 8
b1000000101111011 7
b1011000100101111 6
b101 5
b10000000000000000 4
b10000 3
b100000 2
b100100100001 1
b1100110000100101 0
b1111111010111100 /
b1111011011001011 .
b1111000011111110 -
b1110011110111000 ,
b1101100100101001 +
b1100001011111000 *
b1010001010011001 )
b111011001001101 (
$end
#0
$dumpvars
b0 W
0V
bx U
bx T
bx S
bx R
bx Q
bx P
bx O
b0 N
b0 M
b0 L
b0 K
b0 J
bx I
bx '
bx &
x%
b0 $
0#
1"
1!
$end
#5000
0!
#10000
1#
0"
b0 P
b0 O
b0 Q
1!
#15000
0!
#20000
b0 I
b0 '
0%
b1 W
b0 R
b0 S
bx J
1!
#25000
0!
#30000
b0 &
b0 T
b10000000000000000 U
b11 W
1!
#35000
0!
#40000
b111 W
b0 J
1!
#45000
0!
#50000
b1111 W
1!
#55000
0!
#60000
0#
1V
1!
#65000
0!
#70000
b10000000000000000 $
1#
b1110 W
1!
#75000
0!
#80000
b1101 W
b1000000000000000 N
b1100110000100101 M
b100100100001 L
b10000000000000000 K
1!
#85000
0!
#90000
b1000000000000000 P
b1100110000100101 O
b100100100001 Q
b1011 W
1!
#95000
0!
#100000
b1010110101011011 I
b1101010101000110 '
b111 W
b1000000000000000 R
b1101010101000110 S
1!
#105000
0!
#110000
b1101011010101101 &
0V
b1000000000000000 T
b11010110101011011 U
b1111 W
1!
#115000
0!
#120000
0#
b1101011010101101 J
1V
1!
#125000
0!
#130000
b11111111111111110000000000000000 $
1#
b1110 W
1!
#135000
0!
#140000
b1101 W
b11111111111111111000000000000000 N
b11111111111111110011001111011011 M
b11111111111111111111011011011111 L
1!
#145000
0!
#150000
b11111111111111111000000000000000 P
b11111111111111110011001111011011 O
b11111111111111111111011011011111 Q
b1011 W
1!
#155000
0!
#160000
b11111111111111110101001010100101 I
1%
b111 W
b11111111111111111000000000000000 R
b11111111111111110010101010111010 S
1!
#165000
0!
#170000
b1111111111111111111111111111111111111111111111111101011010101101 &
0V
b11111111111111111000000000000000 T
b101001010100101 U
b1111 W
1!
#175000
0!
#180000
0#
b11111111111111111101011010101101 J
1V
1!
#185000
0!
#190000
b100000000000000000 $
1#
b1110 W
1!
#195000
0!
#200000
b1101 W
b10000000000000000 N
b11001100001001010 M
b1001001000010 L
b1000000000000000000 K
1!
#205000
0!
#210000
b10000000000000000 P
b11001100001001010 O
b100100100001000 Q
b1011 W
1!
#215000
0!
#220000
b1111010000000010 I
b11110000101010010 '
0%
b111 W
b10000000000000000 R
b11110000101010010 S
1!
#225000
0!
#230000
b11111010000000010 &
0V
b10000000000000000 T
b11111010000000010 U
b1111 W
1!
#235000
0!
#240000
0#
b11111010000000010 J
1V
1!
#245000
0!
#250000
b11111111111111100000000000000000 $
1#
b1110 W
1!
#255000
0!
#260000
b1101 W
b11111111111111110000000000000000 N
b11111111111111100110011110110110 M
b11111111111111111110110110111110 L
1!
#265000
0!
#270000
b11111111111111110000000000000000 P
b11111111111111100110011110110110 O
b11111111111111111011011011111000 Q
b1011 W
1!
#275000
0!
#280000
b11111111111111110000101111111110 I
1%
b111 W
b11111111111111110000000000000000 R
b11111111111111100001111010101110 S
1!
#285000
0!
#290000
b1111111111111111111111111111111111111111111111111111010000000010 &
0V
b11111111111111110000000000000000 T
b101111111110 U
b1111 W
1!
#295000
0!
#300000
0#
b11111111111111111111010000000010 J
1V
1!
#305000
0!
#310000
b1000000000000000 $
1#
b1110 W
1!
#315000
0!
#320000
b1101 W
b100000000000000 N
b110011000010010 M
b10010010000 L
b100000000000000 K
1!
#325000
0!
#330000
b100000000000000 P
b110011000010010 O
b100100100 Q
b1011 W
1!
#335000
0!
#340000
b110011100110110 I
b110011100110110 '
0%
b111 W
b100000000000000 R
b110011100110110 S
1!
#345000
0!
#350000
b101100111001101 &
0V
b100000000000000 T
b10110011100110110 U
b1111 W
1!
#355000
0!
#360000
0#
b101100111001101 J
1V
1!
#365000
0!
#370000
b11111111111111111000000000000000 $
1#
b1110 W
1!
#375000
0!
#380000
b1101 W
b11111111111111111100000000000000 N
b11111111111111111001100111101101 M
b11111111111111111111101101101111 L
1!
#385000
0!
#390000
b11111111111111111100000000000000 P
b11111111111111111001100111101101 O
b11111111111111111111111011011011 Q
b1011 W
1!
#395000
0!
#400000
b11111111111111111001100011001000 I
b110011100111000 '
1%
b111 W
b11111111111111111100000000000000 R
b11111111111111111001100011001000 S
1!
#405000
0!
#410000
b1111111111111111111111111111111111111111111111111101100111001110 &
0V
b11111111111111111100000000000000 T
b1001100011001000 U
b1111 W
1!
#415000
0!
#420000
0#
b11111111111111111101100111001110 J
1V
1!
#425000
0!
#430000
b1110 W
1!
#430001
b0 $
1"
#435001
0!
#440001
b0 W
b0 N
b0 M
b0 L
b0 K
b0 J
0V
1!
#445001
0!
#450001
b1010000000000000000 $
1#
0"
b0 P
b0 O
b0 Q
1!
#455001
0!
#460001
b0 I
b0 '
0%
b1 W
b101000000000000000 N
b111111110010111001 M
b10110110100101 L
b110010000000000000000 K
b0 R
b0 S
b11111111111111111101100111001110 J
1!
#465001
0!
#470001
b0 &
b0 T
b10000000000000000 U
b101000000000000000 P
b111111110010111001 O
b1000111010100011101 Q
b11 W
1!
#475001
0!
#480001
b10000000000000000 I
b10000111000111010110 '
b111 W
b101000000000000000 R
b10000111000111010110 S
b0 J
1!
#485001
0!
#490001
b1010000000000000000 &
b101000000000000000 T
b100000000000000000 U
b1111 W
1!
#495001
0!
#500001
0#
b1010000000000000000 J
1V
1!
#505001
0!
#510001
b10000000000000000000 $
1#
b1110 W
1!
#515001
0!
#520001
b1101 W
b1000000000000000000 N
b1100110000100101000 M
b100100100001000 L
b10000000000000000000000 K
1!
#525001
0!
#530001
b1000000000000000000 P
b1100110000100101000 O
b100100100001000000000 Q
b1011 W
1!
#535001
0!
#540001
b110001010001100101000 '
b111 W
b1000000000000000000 R
b110001010001100101000 S
1!
#545001
0!
#550001
b10000000000000000000 &
0V
b1000000000000000000 T
b1111 W
1!
#555001
0!
#560001
0#
b10000000000000000000 J
1V
1!
#565001
0!
#570001
b11111111111110110000000000000000 $
1#
b1110 W
1!
#575001
0!
#580001
b1101 W
b11111111111111011000000000000000 N
b11111111111111000000001101000111 M
b11111111111111111101001001011011 L
b110010000000000000000 K
1!
#585001
0!
#590001
b11111111111111011000000000000000 P
b11111111111111000000001101000111 O
b11111111111110111000101011100011 Q
b1011 W
1!
#595001
0!
#600001
b11111111111111110000000000000000 I
b10000111000111010110 '
1%
b111 W
b11111111111111011000000000000000 R
b11111111111101111000111000101010 S
1!
#605001
0!
#610001
b0 &
0V
b11111111111111011000000000000000 T
b0 U
b1111 W
1!
#615001
0!
#620001
0#
b0 J
1V
1!
#625001
0!
#630001
b11111111111110000000000000000000 $
1#
b1110 W
1!
#635001
0!
#640001
b1101 W
b11111111111111000000000000000000 N
b11111111111110011001111011011000 M
b11111111111111111011011011111000 L
b10000000000000000000000 K
1!
#645001
0!
#650001
b11111111111111000000000000000000 P
b11111111111110011001111011011000 O
b11111111111011011011111000000000 Q
b1011 W
1!
#655001
0!
#660001
b110001010001100101000 '
b111 W
b11111111111111000000000000000000 R
b11111111111001110101110011011000 S
1!
#665001
0!
#670001
0V
b11111111111111000000000000000000 T
b1111 W
1!
#675001
0!
#680001
0#
1V
1!
#685001
0!
#690001
b1110 W
1!
#690002
b0 $
1"
#695002
0!
#700002
b0 W
b0 N
b0 M
b0 L
b0 K
0V
1!
#705002
0!
#710002
b10000000000000000 $
1#
0"
b0 P
b0 O
b0 Q
1!
#715002
0!
#720002
0#
b0 I
b0 '
0%
b1 W
b1000000000000000 N
b1100110000100101 M
b100100100001 L
b10000000000000000 K
b0 R
b0 S
1!
#725002
0!
#730002
b0 T
b10000000000000000 U
b1000000000000000 P
b1100110000100101 O
b100100100001 Q
b10 W
1!
#735002
0!
#740002
b1010110101011011 I
b1101010101000110 '
b100 W
b1000000000000000 R
b1101010101000110 S
1!
#745002
0!
#750002
b1101011010101101 &
b1000000000000000 T
b11010110101011011 U
b1000 W
1!
#755002
0!
#760002
b0 W
b1101011010101101 J
1V
1!
#765002
0!
#770002
0V
1!
#770003
b0 $
1"
#775003
0!
#780003
b0 N
b0 M
b0 L
b0 K
b0 J
1!
#785003
0!
#790003
1#
0"
b0 P
b0 O
b0 Q
1!
#795003
0!
#800003
b0 I
b0 '
b1 W
b0 R
b0 S
b1101011010101101 J
1!
#805003
0!
#810003
b0 &
b0 T
b10000000000000000 U
b11 W
1!
#815003
0!
#820003
b111 W
b0 J
1!
#825003
0!
#830003
b1111 W
1!
#835003
0!
#840003
0#
1V
1!
#845003
0!
#850003
b1110 W
1!
#850004
1"
#855004
0!
#860004
b0 W
0V
1!
#865004
0!
#870004
b1000000000000000 $
1#
0"
1!
#875004
0!
#880004
b10000000000000000 $
b1 W
b100000000000000 N
b110011000010010 M
b10010010000 L
b100000000000000 K
1!
#885004
0!
#890004
b11000000000000000 $
b100000000000000 P
b110011000010010 O
b100100100 Q
b1000000000000000 N
b1100110000100101 M
b100100100001 L
b10000000000000000 K
b11 W
1!
#895004
0!
#900004
b100000000000000000 $
b110011100110110 I
b110011100110110 '
b111 W
b1100000000000000 N
b10011001000110111 M
b110110110001 L
b100100000000000000 K
b1000000000000000 P
b1100110000100101 O
b100100100001 Q
b100000000000000 R
b110011100110110 S
1!
#905004
0!
#910004
b11111111111111111000000000000000 $
b101100111001101 &
b1010110101011011 I
b1101010101000110 '
b100000000000000 T
b10110011100110110 U
b1000000000000000 R
b1101010101000110 S
b1100000000000000 P
b10011001000110111 O
b1111011001110 Q
b10000000000000000 N
b11001100001001010 M
b1001001000010 L
b1000000000000000000 K
b1111 W
1!
#915004
0!
#920004
b11111111111111110000000000000000 $
b1101110100001000 I
b10101000100000101 '
b1101011010101101 &
b11111111111111111100000000000000 N
b11111111111111111001100111101101 M
b11111111111111111111101101101111 L
b100000000000000 K
b10000000000000000 P
b11001100001001010 O
b100100100001000 Q
b1100000000000000 R
b10101000100000101 S
b1000000000000000 T
b11010110101011011 U
b101100111001101 J
1V
1!
#925004
0!
#930004
b11111111111111101000000000000000 $
b10110010111000110 &
b1111010000000010 I
b11110000101010010 '
b1101011010101101 J
b1100000000000000 T
b11101110100001000 U
b10000000000000000 R
b11110000101010010 S
b11111111111111111100000000000000 P
b11111111111111111001100111101101 O
b11111111111111111111111011011011 Q
b11111111111111111000000000000000 N
b11111111111111110011001111011011 M
b11111111111111111111011011011111 L
b10000000000000000 K
1!
#935004
0!
#940004
b11111111111111100000000000000000 $
b11111111111111111001100011001000 I
b110011100111000 '
1%
b11111010000000010 &
b11111111111111110100000000000000 N
b11111111111111101100110111001000 M
b11111111111111111111001001001110 L
b100100000000000000 K
b11111111111111111000000000000000 P
b11111111111111110011001111011011 O
b11111111111111111111011011011111 Q
b11111111111111111100000000000000 R
b11111111111111111001100011001000 S
b10000000000000000 T
b11111010000000010 U
b10110010111000110 J
1!
#945004
0!
#950004
0#
b1111111111111111111111111111111111111111111111111101100111001110 &
b11111111111111110101001010100101 I
b1101010101000110 '
b11111010000000010 J
b11111111111111111100000000000000 T
b1001100011001000 U
b11111111111111111000000000000000 R
b11111111111111110010101010111010 S
b11111111111111110100000000000000 P
b11111111111111101100110111001000 O
b11111111111111111110000100101111 Q
b11111111111111110000000000000000 N
b11111111111111100110011110110110 M
b11111111111111111110110110111110 L
b1000000000000000000 K
1!
#955004
0!
#960004
b11111111111111110010001011111000 I
b10101000100001001 '
b1111111111111111111111111111111111111111111111111101011010101101 &
b1110 W
b11111111111111110000000000000000 P
b11111111111111100110011110110110 O
b11111111111111111011011011111000 Q
b11111111111111110100000000000000 R
b11111111111111101010111011110111 S
b11111111111111111000000000000000 T
b101001010100101 U
b11111111111111111101100111001110 J
1!
#965004
0!
#970004
b1111111111111111111111111111111111111111111111111110010111000110 &
b11111111111111110000101111111110 I
b11110000101010010 '
b11111111111111111101011010101101 J
b11111111111111110100000000000000 T
b10001011111000 U
b11111111111111110000000000000000 R
b11111111111111100001111010101110 S
b1100 W
1!
#975004
0!
#980004
b1111111111111111111111111111111111111111111111111111010000000010 &
b1000 W
b11111111111111110000000000000000 T
b101111111110 U
b11111111111111111110010111000110 J
1!
#985004
0!
#990004
b11111111111111111111010000000010 J
b0 W
1!
#995004
0!
#1000004
0V
1!
