project/m2/rtl/compute_core_p3.sv
// =========================================================================
// Module:  compute_core (Pipelined GELU - Parallel PWL)
// Description:
//   3-stage pipelined GELU activation function using a 16-segment 
//   parallel Piecewise-Linear (PWL) approximation.
// Data Format: 32-bit signed fixed point, Q16.16
// =========================================================================

module compute_core #(
    parameter int DATA_WIDTH = 32,
    parameter int FRAC_BITS  = 16,
    parameter int PIPE_DEPTH = 3
)(
    input  logic                        clk,
    input  logic                        rst,
    input  logic                        valid_in,
    input  logic signed [DATA_WIDTH-1:0] x,
    output logic                        valid_out,
    output logic signed [DATA_WIDTH-1:0] out
);

    // -------------------------------------------------------------------------
    // Threshold Constants (Q16.16) - Every 0.5 steps from -3.5 to 3.5
    // -------------------------------------------------------------------------
    localparam signed [DATA_WIDTH-1:0] T_N35 = -32'sd229376; // -3.5
    localparam signed [DATA_WIDTH-1:0] T_N30 = -32'sd196608; // -3.0
    localparam signed [DATA_WIDTH-1:0] T_N25 = -32'sd163840; // -2.5
    localparam signed [DATA_WIDTH-1:0] T_N20 = -32'sd131072; // -2.0
    localparam signed [DATA_WIDTH-1:0] T_N15 = -32'sd98304;  // -1.5
    localparam signed [DATA_WIDTH-1:0] T_N10 = -32'sd65536;  // -1.0
    localparam signed [DATA_WIDTH-1:0] T_N05 = -32'sd32768;  // -0.5
    localparam signed [DATA_WIDTH-1:0] T_000 =  32'sd0;      //  0.0
    localparam signed [DATA_WIDTH-1:0] T_P05 =  32'sd32768;  //  0.5
    localparam signed [DATA_WIDTH-1:0] T_P10 =  32'sd65536;  //  1.0
    localparam signed [DATA_WIDTH-1:0] T_P15 =  32'sd98304;  //  1.5
    localparam signed [DATA_WIDTH-1:0] T_P20 =  32'sd131072; //  2.0
    localparam signed [DATA_WIDTH-1:0] T_P25 =  32'sd163840; //  2.5
    localparam signed [DATA_WIDTH-1:0] T_P30 =  32'sd196608; //  3.0
    localparam signed [DATA_WIDTH-1:0] T_P35 =  32'sd229376; //  3.5

    // -------------------------------------------------------------------------
    // Valid Shift Register
    // -------------------------------------------------------------------------
    logic [PIPE_DEPTH-2:0] valid_pipe;
    always_ff @(posedge clk) begin
        if (rst) valid_pipe <= '0;
        else     valid_pipe <= {valid_pipe[PIPE_DEPTH-3:0], valid_in};
    end

    // =========================================================================
    // STAGE 1: Parallel Comparison (The "Flash" Stage)
    // =========================================================================
    logic signed [DATA_WIDTH-1:0] s1_x;
    logic [15:0] s1_region_hit; 

    always_ff @(posedge clk) begin
        s1_x <= x; // Latch input
        
        // Parallel comparators - evaluates in a single cycle
        s1_region_hit[0]  <= (x < T_N30);
        s1_region_hit[1]  <= (x >= T_N30 && x < T_N25);
        s1_region_hit[2]  <= (x >= T_N25 && x < T_N20);
        s1_region_hit[3]  <= (x >= T_N20 && x < T_N15);
        s1_region_hit[4]  <= (x >= T_N15 && x < T_N10);
        s1_region_hit[5]  <= (x >= T_N10 && x < T_N05);
        s1_region_hit[6]  <= (x >= T_N05 && x < T_000);
        s1_region_hit[7]  <= (x >= T_000 && x < T_P05);
        s1_region_hit[8]  <= (x >= T_P05 && x < T_P10);
        s1_region_hit[9]  <= (x >= T_P10 && x < T_P15);
        s1_region_hit[10] <= (x >= T_P15 && x < T_P20);
        s1_region_hit[11] <= (x >= T_P20 && x < T_P25);
        s1_region_hit[12] <= (x >= T_P25 && x < T_P30);
        s1_region_hit[13] <= (x >= T_P30 && x < T_P35);
        s1_region_hit[14] <= (x >= T_P35);
    end

    // =========================================================================
    // STAGE 2: One-Hot Selection & Subtraction
    // =========================================================================
    logic signed [DATA_WIDTH-1:0] s2_slope;
    logic signed [DATA_WIDTH-1:0] s2_base;
    logic signed [DATA_WIDTH-1:0] s2_dx;

    logic signed [DATA_WIDTH-1:0] comb_slope, comb_base, comb_thresh;

    always_comb begin
        // Default to linear pass-through (x >= 3.5 roughly equals x)
        comb_slope  = 32'sd65536; 
        comb_base   = 32'sd0;
        comb_thresh = 32'sd0;

        // 'unique case' forces parallel MUX synthesis rather than a priority chain
        unique case (1'b1)
            s1_region_hit[0]:  begin comb_slope = 32'sd0;     comb_base = 32'sd0;      comb_thresh = 32'sd0;   end // < -3.0 (Zero)
            s1_region_hit[1]:  begin comb_slope = 32'sd200;   comb_base = -32'sd262;   comb_thresh = T_N30;    end // [-3.0, -2.5)
            s1_region_hit[2]:  begin comb_slope = 32'sd1966;  comb_base = -32'sd983;   comb_thresh = T_N25;    end // [-2.5, -2.0)
            s1_region_hit[3]:  begin comb_slope = 32'sd3604;  comb_base = -32'sd2949;  comb_thresh = T_N20;    end // [-2.0, -1.5)
            s1_region_hit[4]:  begin comb_slope = 32'sd3801;  comb_base = -32'sd6553;  comb_thresh = T_N15;    end // [-1.5, -1.0)
            s1_region_hit[5]:  begin comb_slope = 32'sd262;   comb_base = -32'sd10354; comb_thresh = T_N10;    end // [-1.0, -0.5)
            s1_region_hit[6]:  begin comb_slope = 32'sd10092; comb_base = -32'sd10092; comb_thresh = T_N05;    end // [-0.5, 0.0)
            s1_region_hit[7]:  begin comb_slope = 32'sd22609; comb_base = 32'sd0;      comb_thresh = T_000;    end // [0.0, 0.5)
            s1_region_hit[8]:  begin comb_slope = 32'sd32505; comb_base = 32'sd22609;  comb_thresh = T_P05;    end // [0.5, 1.0)
            s1_region_hit[9]:  begin comb_slope = 32'sd36569; comb_base = 32'sd55115;  comb_thresh = T_P10;    end // [1.0, 1.5)
            s1_region_hit[10]: begin comb_slope = 32'sd36372; comb_base = 32'sd91684;  comb_thresh = T_P15;    end // [1.5, 2.0)
            s1_region_hit[11]: begin comb_slope = 32'sd34734; comb_base = 32'sd128057; comb_thresh = T_P20;    end // [2.0, 2.5)
            s1_region_hit[12]: begin comb_slope = 32'sd33423; comb_base = 32'sd162791; comb_thresh = T_P25;    end // [2.5, 3.0)
            s1_region_hit[13]: begin comb_slope = 32'sd33030; comb_base = 32'sd196214; comb_thresh = T_P30;    end // [3.0, 3.5)
            s1_region_hit[14]: begin comb_slope = 32'sd65536; comb_base = 32'sd0;      comb_thresh = 32'sd0;   end // >= 3.5 (Linear y=x)
            default:           begin comb_slope = 32'sd65536; comb_base = 32'sd0;      comb_thresh = 32'sd0;   end 
        endcase
    end

    always_ff @(posedge clk) begin
        s2_slope <= comb_slope;
        s2_base  <= comb_base;
        // Subtractor pulled out of the branches to save logic area
        if (s1_region_hit[14] || s1_region_hit[0]) begin
            s2_dx <= s1_x; // Pass raw X for tails
        end else begin
            s2_dx <= s1_x - comb_thresh;
        end
    end

    // =========================================================================
    // STAGE 3: Compute & Saturate
    // =========================================================================
    logic signed [63:0] s3_mult_full;

    // Single DSP multiplier used here
    assign s3_mult_full = ($signed(64'(s2_slope)) * $signed(64'(s2_dx))) >>> FRAC_BITS;

    always_ff @(posedge clk) begin
        if (rst) begin
            valid_out <= 1'b0;
            out       <= '0;
        end else begin
            valid_out <= valid_pipe[PIPE_DEPTH-2];
            
            // Saturation logic
            if ((s3_mult_full + s2_base) > 64'sd2147483647)
                out <= 32'sd2147483647;
            else if ((s3_mult_full + s2_base) < -64'sd2147483648)
                out <= -32'sd2147483648;
            else
                out <= s3_mult_full[31:0] + s2_base;
        end
    end
    // -------------------------------------------------------------------------
    // Simulation hooks
    // -------------------------------------------------------------------------
    initial begin
        $dumpfile("dump.vcd"); 
        $dumpvars(0, compute_core);     
    end
endmodule

project/m2/sim/compute_core_run.vcd
$date
	Wed May  6 20:59:13 2026
$end
$version
	Icarus Verilog
$end
$timescale
	1ps
$end
$scope module compute_core $end
$var wire 1 ! clk $end
$var wire 1 " rst $end
$var wire 1 # valid_in $end
$var wire 32 $ x [31:0] $end
$var wire 64 % s3_mult_full [63:0] $end
$var parameter 32 & DATA_WIDTH $end
$var parameter 32 ' FRAC_BITS $end
$var parameter 32 ( PIPE_DEPTH $end
$var parameter 32 ) T_000 $end
$var parameter 32 * T_N05 $end
$var parameter 32 + T_N10 $end
$var parameter 32 , T_N15 $end
$var parameter 32 - T_N20 $end
$var parameter 32 . T_N25 $end
$var parameter 32 / T_N30 $end
$var parameter 32 0 T_N35 $end
$var parameter 32 1 T_P05 $end
$var parameter 32 2 T_P10 $end
$var parameter 32 3 T_P15 $end
$var parameter 32 4 T_P20 $end
$var parameter 32 5 T_P25 $end
$var parameter 32 6 T_P30 $end
$var parameter 32 7 T_P35 $end
$var reg 32 8 comb_base [31:0] $end
$var reg 32 9 comb_slope [31:0] $end
$var reg 32 : comb_thresh [31:0] $end
$var reg 32 ; out [31:0] $end
$var reg 16 < s1_region_hit [15:0] $end
$var reg 32 = s1_x [31:0] $end
$var reg 32 > s2_base [31:0] $end
$var reg 32 ? s2_dx [31:0] $end
$var reg 32 @ s2_slope [31:0] $end
$var reg 1 A valid_out $end
$var reg 2 B valid_pipe [1:0] $end
$upscope $end
$enddefinitions $end
$comment Show the parameter values. $end
$dumpall
b111000000000000000 7
b110000000000000000 6
b101000000000000000 5
b100000000000000000 4
b11000000000000000 3
b10000000000000000 2
b1000000000000000 1
b11111111111111001000000000000000 0
b11111111111111010000000000000000 /
b11111111111111011000000000000000 .
b11111111111111100000000000000000 -
b11111111111111101000000000000000 ,
b11111111111111110000000000000000 +
b11111111111111111000000000000000 *
b0 )
b11 (
b10000 '
b100000 &
$end
#0
$dumpvars
b0 B
0A
b10000000000000000 @
bx ?
b0 >
b0 =
bx000000010000000 <
b0 ;
b0 :
b101100001010001 9
b0 8
bx %
b0 $
0#
1"
1!
$end
#5000
0!
#10000
b11111111111111000000000000000000 $
1#
0"
b0 %
b0 ?
b101100001010001 @
1!
#15000
0!
#20000
b11111111111111000000110011001101 $
b0 9
b1 B
bx000000000000001 <
b11111111111111000000000000000000 =
1!
#25000
0!
#30000
b11111111111111000001100110011010 $
b11111111111111000000000000000000 ?
b0 @
b11111111111111000000110011001101 =
b11 B
1!
#35000
0!
#40000
b11111111111111000010011001100110 $
b11111111111111000001100110011010 =
b11111111111111000000110011001101 ?
1A
1!
#45000
0!
#50000
b11111111111111000011001100110011 $
b11111111111111000001100110011010 ?
b11111111111111000010011001100110 =
1!
#55000
0!
#60000
b11111111111111000100000000000000 $
b11111111111111000011001100110011 =
b11111111111111000010011001100110 ?
1!
#65000
0!
#70000
b11111111111111000100110011001101 $
b11111111111111000011001100110011 ?
b11111111111111000100000000000000 =
1!
#75000
0!
#80000
b11111111111111000101100110011010 $
b11111111111111000100110011001101 =
b11111111111111000100000000000000 ?
1!
#85000
0!
#90000
b11111111111111000110011001100110 $
b11111111111111000100110011001101 ?
b11111111111111000101100110011010 =
1!
#95000
0!
#100000
b11111111111111000111001100110011 $
b11111111111111000110011001100110 =
b11111111111111000101100110011010 ?
1!
#105000
0!
#110000
b11111111111111001000000000000000 $
b11111111111111000110011001100110 ?
b11111111111111000111001100110011 =
1!
#115000
0!
#120000
b11111111111111001000110011001101 $
b11111111111111001000000000000000 =
b11111111111111000111001100110011 ?
1!
#125000
0!
#130000
b11111111111111001001100110011010 $
b11111111111111001000000000000000 ?
b11111111111111001000110011001101 =
1!
#135000
0!
#140000
b11111111111111001010011001100110 $
b11111111111111001001100110011010 =
b11111111111111001000110011001101 ?
1!
#145000
0!
#150000
b11111111111111001011001100110011 $
b11111111111111001001100110011010 ?
b11111111111111001010011001100110 =
1!
#155000
0!
#160000
b11111111111111001100000000000000 $
b11111111111111001011001100110011 =
b11111111111111001010011001100110 ?
1!
#165000
0!
#170000
b11111111111111001100110011001101 $
b11111111111111001011001100110011 ?
b11111111111111001100000000000000 =
1!
#175000
0!
#180000
b11111111111111001101100110011010 $
b11111111111111001100110011001101 =
b11111111111111001100000000000000 ?
1!
#185000
0!
#190000
b11111111111111001110011001100110 $
b11111111111111001100110011001101 ?
b11111111111111001101100110011010 =
1!
#195000
0!
#200000
b11111111111111001111001100110011 $
b11111111111111001110011001100110 =
b11111111111111001101100110011010 ?
1!
#205000
0!
#210000
b11111111111111010000000000000000 $
b11111111111111001110011001100110 ?
b11111111111111001111001100110011 =
1!
#215000
0!
#220000
b11111111111111010000110011001101 $
b11111111111111010000000000000000 :
b11111111111111111111111011111010 8
b11001000 9
bx000000000000010 <
b11111111111111010000000000000000 =
b11111111111111001111001100110011 ?
1!
#225000
0!
#230000
b11111111111111010001100110011010 $
b0 ?
b11111111111111111111111011111010 >
b11001000 @
b11111111111111010000110011001101 =
1!
#235000
0!
#240000
b11111111111111010010011001100110 $
b1010 %
b11111111111111010001100110011010 =
b110011001101 ?
b11111111111111111111111011111010 ;
1!
#245000
0!
#250000
b11111111111111010011001100110011 $
b10100 %
b11111111111111111111111100000100 ;
b1100110011010 ?
b11111111111111010010011001100110 =
1!
#255000
0!
#260000
b11111111111111010100000000000000 $
b11101 %
b11111111111111010011001100110011 =
b10011001100110 ?
b11111111111111111111111100001110 ;
1!
#265000
0!
#270000
b11111111111111010100110011001101 $
b100111 %
b11111111111111111111111100010111 ;
b11001100110011 ?
b11111111111111010100000000000000 =
1!
#275000
0!
#280000
b11111111111111010101100110011010 $
b110010 %
b11111111111111010100110011001101 =
b100000000000000 ?
b11111111111111111111111100100001 ;
1!
#285000
0!
#290000
b11111111111111010110011001100110 $
b111100 %
b11111111111111111111111100101100 ;
b100110011001101 ?
b11111111111111010101100110011010 =
1!
#295000
0!
#300000
b11111111111111010111001100110011 $
b1000110 %
b11111111111111010110011001100110 =
b101100110011010 ?
b11111111111111111111111100110110 ;
1!
#305000
0!
#310000
b11111111111111011000000000000000 $
b1001111 %
b11111111111111111111111101000000 ;
b110011001100110 ?
b11111111111111010111001100110011 =
1!
#315000
0!
#320000
b11111111111111011000110011001101 $
b11111111111111011000000000000000 :
b11111111111111111111110000101001 8
b11110101110 9
b1011001 %
bx000000000000100 <
b11111111111111011000000000000000 =
b111001100110011 ?
b11111111111111111111111101001001 ;
1!
#325000
0!
#330000
b11111111111111011001100110011010 $
b0 %
b11111111111111111111111101010011 ;
b0 ?
b11111111111111111111110000101001 >
b11110101110 @
b11111111111111011000110011001101 =
1!
#335000
0!
#340000
b11111111111111011010011001100110 $
b1100010 %
b11111111111111011001100110011010 =
b110011001101 ?
b11111111111111111111110000101001 ;
1!
#345000
0!
#350000
b11111111111111011011001100110011 $
b11000100 %
b11111111111111111111110010001011 ;
b1100110011010 ?
b11111111111111011010011001100110 =
1!
#355000
0!
#360000
b11111111111111011100000000000000 $
b100100110 %
b11111111111111011011001100110011 =
b10011001100110 ?
b11111111111111111111110011101101 ;
1!
#365000
0!
#370000
b11111111111111011100110011001101 $
b110001001 %
b11111111111111111111110101001111 ;
b11001100110011 ?
b11111111111111011100000000000000 =
1!
#375000
0!
#380000
b11111111111111011101100110011010 $
b111101011 %
b11111111111111011100110011001101 =
b100000000000000 ?
b11111111111111111111110110110010 ;
1!
#385000
0!
#390000
b11111111111111011110011001100110 $
b1001001101 %
b11111111111111111111111000010100 ;
b100110011001101 ?
b11111111111111011101100110011010 =
1!
#395000
0!
#400000
b11111111111111011111001100110011 $
b1010110000 %
b11111111111111011110011001100110 =
b101100110011010 ?
b11111111111111111111111001110110 ;
1!
#405000
0!
#410000
b11111111111111100000000000000000 $
b1100010010 %
b11111111111111111111111011011001 ;
b110011001100110 ?
b11111111111111011111001100110011 =
1!
#415000
0!
#420000
b11111111111111100000110011001101 $
b11111111111111100000000000000000 :
b11111111111111111111010001111011 8
b111000010100 9
b1101110100 %
bx000000000001000 <
b11111111111111100000000000000000 =
b111001100110011 ?
b11111111111111111111111100111011 ;
1!
#425000
0!
#430000
b11111111111111100001100110011010 $
b0 %
b11111111111111111111111110011101 ;
b0 ?
b11111111111111111111010001111011 >
b111000010100 @
b11111111111111100000110011001101 =
1!
#435000
0!
#440000
b11111111111111100010011001100110 $
b10110100 %
b11111111111111100001100110011010 =
b110011001101 ?
b11111111111111111111010001111011 ;
1!
#445000
0!
#450000
b11111111111111100011001100110011 $
b101101000 %
b11111111111111111111010100101111 ;
b1100110011010 ?
b11111111111111100010011001100110 =
1!
#455000
0!
#460000
b11111111111111100100000000000000 $
b1000011100 %
b11111111111111100011001100110011 =
b10011001100110 ?
b11111111111111111111010111100011 ;
1!
#465000
0!
#470000
b11111111111111100100110011001101 $
b1011010000 %
b11111111111111111111011010010111 ;
b11001100110011 ?
b11111111111111100100000000000000 =
1!
#475000
0!
#480000
b11111111111111100101100110011010 $
b1110000101 %
b11111111111111100100110011001101 =
b100000000000000 ?
b11111111111111111111011101001011 ;
1!
#485000
0!
#490000
b11111111111111100110011001100110 $
b10000111001 %
b11111111111111111111100000000000 ;
b100110011001101 ?
b11111111111111100101100110011010 =
1!
#495000
0!
#500000
b11111111111111100111001100110011 $
b10011101101 %
b11111111111111100110011001100110 =
b101100110011010 ?
b11111111111111111111100010110100 ;
1!
#505000
0!
#510000
b11111111111111101000000000000000 $
b10110100001 %
b11111111111111111111100101101000 ;
b110011001100110 ?
b11111111111111100111001100110011 =
1!
#515000
0!
#520000
b11111111111111101000110011001101 $
b11111111111111101000000000000000 :
b11111111111111111110011001100111 8
b111011011001 9
b11001010101 %
bx000000000010000 <
b11111111111111101000000000000000 =
b111001100110011 ?
b11111111111111111111101000011100 ;
1!
#525000
0!
#530000
b11111111111111101001100110011010 $
b0 %
b11111111111111111111101011010000 ;
b0 ?
b11111111111111111110011001100111 >
b111011011001 @
b11111111111111101000110011001101 =
1!
#535000
0!
#540000
b11111111111111101010011001100110 $
b10111110 %
b11111111111111101001100110011010 =
b110011001101 ?
b11111111111111111110011001100111 ;
1!
#545000
0!
#550000
b11111111111111101011001100110011 $
b101111100 %
b11111111111111111110011100100101 ;
b1100110011010 ?
b11111111111111101010011001100110 =
1!
#555000
0!
#560000
b11111111111111101100000000000000 $
b1000111010 %
b11111111111111101011001100110011 =
b10011001100110 ?
b11111111111111111110011111100011 ;
1!
#565000
0!
#570000
b11111111111111101100110011001101 $
b1011111000 %
b11111111111111111110100010100001 ;
b11001100110011 ?
b11111111111111101100000000000000 =
1!
#575000
0!
#580000
b11111111111111101101100110011010 $
b1110110110 %
b11111111111111101100110011001101 =
b100000000000000 ?
b11111111111111111110100101011111 ;
1!
#585000
0!
#590000
b11111111111111101110011001100110 $
b10001110100 %
b11111111111111111110101000011101 ;
b100110011001101 ?
b11111111111111101101100110011010 =
1!
#595000
0!
#600000
b11111111111111101111001100110011 $
b10100110010 %
b11111111111111101110011001100110 =
b101100110011010 ?
b11111111111111111110101011011011 ;
1!
#605000
0!
#610000
b11111111111111110000000000000000 $
b10111110000 %
b11111111111111111110101110011001 ;
b110011001100110 ?
b11111111111111101111001100110011 =
1!
#615000
0!
#620000
b11111111111111110000110011001101 $
b11111111111111110000000000000000 :
b11111111111111111101011110001110 8
b100000110 9
b11010101110 %
bx000000000100000 <
b11111111111111110000000000000000 =
b111001100110011 ?
b11111111111111111110110001010111 ;
1!
#625000
0!
#630000
b11111111111111110001100110011010 $
b0 %
b11111111111111111110110100010101 ;
b0 ?
b11111111111111111101011110001110 >
b100000110 @
b11111111111111110000110011001101 =
1!
#635000
0!
#640000
b11111111111111110010011001100110 $
b1101 %
b11111111111111110001100110011010 =
b110011001101 ?
b11111111111111111101011110001110 ;
1!
#645000
0!
#650000
b11111111111111110011001100110011 $
b11010 %
b11111111111111111101011110011011 ;
b1100110011010 ?
b11111111111111110010011001100110 =
1!
#655000
0!
#660000
b11111111111111110100000000000000 $
b100111 %
b11111111111111110011001100110011 =
b10011001100110 ?
b11111111111111111101011110101000 ;
1!
#665000
0!
#670000
b11111111111111110100110011001101 $
b110100 %
b11111111111111111101011110110101 ;
b11001100110011 ?
b11111111111111110100000000000000 =
1!
#675000
0!
#680000
b11111111111111110101100110011010 $
b1000001 %
b11111111111111110100110011001101 =
b100000000000000 ?
b11111111111111111101011111000010 ;
1!
#685000
0!
#690000
b11111111111111110110011001100110 $
b1001110 %
b11111111111111111101011111001111 ;
b100110011001101 ?
b11111111111111110101100110011010 =
1!
#695000
0!
#700000
b11111111111111110111001100110011 $
b1011011 %
b11111111111111110110011001100110 =
b101100110011010 ?
b11111111111111111101011111011100 ;
1!
#705000
0!
#710000
b11111111111111111000000000000000 $
b1101000 %
b11111111111111111101011111101001 ;
b110011001100110 ?
b11111111111111110111001100110011 =
1!
#715000
0!
#720000
b11111111111111111000110011001101 $
b11111111111111111000000000000000 :
b11111111111111111101100010010100 8
b10011101101100 9
b1110101 %
bx000000001000000 <
b11111111111111111000000000000000 =
b111001100110011 ?
b11111111111111111101011111110110 ;
1!
#725000
0!
#730000
b11111111111111111001100110011010 $
b0 %
b11111111111111111101100000000011 ;
b0 ?
b11111111111111111101100010010100 >
b10011101101100 @
b11111111111111111000110011001101 =
1!
#735000
0!
#740000
b11111111111111111010011001100110 $
b111111000 %
b11111111111111111001100110011010 =
b110011001101 ?
b11111111111111111101100010010100 ;
1!
#745000
0!
#750000
b11111111111111111011001100110011 $
b1111110001 %
b11111111111111111101101010001100 ;
b1100110011010 ?
b11111111111111111010011001100110 =
1!
#755000
0!
#760000
b11111111111111111100000000000000 $
b10111101001 %
b11111111111111111011001100110011 =
b10011001100110 ?
b11111111111111111101110010000101 ;
1!
#765000
0!
#770000
b11111111111111111100110011001101 $
b11111100010 %
b11111111111111111101111001111101 ;
b11001100110011 ?
b11111111111111111100000000000000 =
1!
#775000
0!
#780000
b11111111111111111101100110011010 $
b100111011011 %
b11111111111111111100110011001101 =
b100000000000000 ?
b11111111111111111110000001110110 ;
1!
#785000
0!
#790000
b11111111111111111110011001100110 $
b101111010011 %
b11111111111111111110001001101111 ;
b100110011001101 ?
b11111111111111111101100110011010 =
1!
#795000
0!
#800000
b11111111111111111111001100110011 $
b110111001100 %
b11111111111111111110011001100110 =
b101100110011010 ?
b11111111111111111110010001100111 ;
1!
#805000
0!
#810000
b0 $
b111111000100 %
b11111111111111111110011001100000 ;
b110011001100110 ?
b11111111111111111111001100110011 =
1!
#815000
0!
#820000
b110011001101 $
b0 :
b0 8
b101100001010001 9
b1000110111101 %
bx000000010000000 <
b0 =
b111001100110011 ?
b11111111111111111110100001011000 ;
1!
#825000
0!
#830000
b1100110011010 $
b0 %
b11111111111111111110101001010001 ;
b0 ?
b0 >
b101100001010001 @
b110011001101 =
1!
#835000
0!
#840000
b10011001100110 $
b10001101010 %
b1100110011010 =
b110011001101 ?
b0 ;
1!
#845000
0!
#850000
b11001100110011 $
b100011010101 %
b10001101010 ;
b1100110011010 ?
b10011001100110 =
1!
#855000
0!
#860000
b100000000000000 $
b110100111111 %
b11001100110011 =
b10011001100110 ?
b100011010101 ;
1!
#865000
0!
#870000
b100110011001101 $
b1000110101001 %
b110100111111 ;
b11001100110011 ?
b100000000000000 =
1!
#875000
0!
#880000
b101100110011010 $
b1011000010100 %
b100110011001101 =
b100000000000000 ?
b1000110101001 ;
1!
#885000
0!
#890000
b110011001100110 $
b1101001111110 %
b1011000010100 ;
b100110011001101 ?
b101100110011010 =
1!
#895000
0!
#900000
b111001100110011 $
b1111011101001 %
b110011001100110 =
b101100110011010 ?
b1101001111110 ;
1!
#905000
0!
#910000
b1000000000000000 $
b10001101010011 %
b1111011101001 ;
b110011001100110 ?
b111001100110011 =
1!
#915000
0!
#920000
b1000110011001101 $
b1000000000000000 :
b101100001010001 8
b111111011111001 9
b10011110111101 %
bx000000100000000 <
b1000000000000000 =
b111001100110011 ?
b10001101010011 ;
1!
#925000
0!
#930000
b1001100110011010 $
b0 %
b10011110111101 ;
b0 ?
b101100001010001 >
b111111011111001 @
b1000110011001101 =
1!
#935000
0!
#940000
b1010011001100110 $
b11001011001 %
b1001100110011010 =
b110011001101 ?
b101100001010001 ;
1!
#945000
0!
#950000
b1011001100110011 $
b110010110010 %
b101111010101010 ;
b1100110011010 ?
b1010011001100110 =
1!
#955000
0!
#960000
b1100000000000000 $
b1001100001011 %
b1011001100110011 =
b10011001100110 ?
b110010100000011 ;
1!
#965000
0!
#970000
b1100110011001101 $
b1100101100100 %
b110101101011100 ;
b11001100110011 ?
b1100000000000000 =
1!
#975000
0!
#980000
b1101100110011010 $
b1111110111110 %
b1100110011001101 =
b100000000000000 ?
b111000110110101 ;
1!
#985000
0!
#990000
b1110011001100110 $
b10011000010111 %
b111100000001111 ;
b100110011001101 ?
b1101100110011010 =
1!
#995000
0!
#1000000
b1111001100110011 $
b10110001110000 %
b1110011001100110 =
b101100110011010 ?
b111111001101000 ;
1!
#1005000
0!
#1010000
b10000000000000000 $
b11001011001001 %
b1000010011000001 ;
b110011001100110 ?
b1111001100110011 =
1!
#1015000
0!
#1020000
b10000110011001101 $
b10000000000000000 :
b1101011101001011 8
b1000111011011001 9
b11100100100011 %
bx000001000000000 <
b10000000000000000 =
b111001100110011 ?
b1000101100011010 ;
1!
#1025000
0!
#1030000
b10001100110011010 $
b0 %
b1001000101110100 ;
b0 ?
b1101011101001011 >
b1000111011011001 @
b10000110011001101 =
1!
#1035000
0!
#1040000
b10010011001100110 $
b11100100100 %
b10001100110011010 =
b110011001101 ?
b1101011101001011 ;
1!
#1045000
0!
#1050000
b10011001100110011 $
b111001001001 %
b1101111001101111 ;
b1100110011010 ?
b10010011001100110 =
1!
#1055000
0!
#1060000
b10100000000000000 $
b1010101101101 %
b10011001100110011 =
b10011001100110 ?
b1110010110010100 ;
1!
#1065000
0!
#1070000
b10100110011001101 $
b1110010010001 %
b1110110010111000 ;
b11001100110011 ?
b10100000000000000 =
1!
#1075000
0!
#1080000
b10101100110011010 $
b10001110110110 %
b10100110011001101 =
b100000000000000 ?
b1111001111011100 ;
1!
#1085000
0!
#1090000
b10110011001100110 $
b10101011011010 %
b1111101100000001 ;
b100110011001101 ?
b10101100110011010 =
1!
#1095000
0!
#1100000
b10111001100110011 $
b11000111111111 %
b10110011001100110 =
b101100110011010 ?
b10000001000100101 ;
1!
#1105000
0!
#1110000
b11000000000000000 $
b11100100100011 %
b10000100101001010 ;
b110011001100110 ?
b10111001100110011 =
1!
#1115000
0!
#1120000
b11000110011001101 $
b11000000000000000 :
b10110011000100100 8
b1000111000010100 9
b100000001000111 %
bx000010000000000 <
b11000000000000000 =
b111001100110011 ?
b10001000001101110 ;
1!
#1125000
0!
#1130000
b11001100110011010 $
b0 %
b10001011110010010 ;
b0 ?
b10110011000100100 >
b1000111000010100 @
b11000110011001101 =
1!
#1135000
0!
#1140000
b11010011001100110 $
b11100011010 %
b11001100110011010 =
b110011001101 ?
b10110011000100100 ;
1!
#1145000
0!
#1150000
b11011001100110011 $
b111000110101 %
b10110110100111110 ;
b1100110011010 ?
b11010011001100110 =
1!
#1155000
0!
#1160000
b11100000000000000 $
b1010101001111 %
b11011001100110011 =
b10011001100110 ?
b10111010001011001 ;
1!
#1165000
0!
#1170000
b11100110011001101 $
b1110001101010 %
b10111101101110011 ;
b11001100110011 ?
b11100000000000000 =
1!
#1175000
0!
#1180000
b11101100110011010 $
b10001110000101 %
b11100110011001101 =
b100000000000000 ?
b11000001010001110 ;
1!
#1185000
0!
#1190000
b11110011001100110 $
b10101010011111 %
b11000100110101001 ;
b100110011001101 ?
b11101100110011010 =
1!
#1195000
0!
#1200000
b11111001100110011 $
b11000110111010 %
b11110011001100110 =
b101100110011010 ?
b11001000011000011 ;
1!
#1205000
0!
#1210000
b100000000000000000 $
b11100011010100 %
b11001011111011110 ;
b110011001100110 ?
b11111001100110011 =
1!
#1215000
0!
#1220000
b100000110011001101 $
b100000000000000000 :
b11111010000111001 8
b1000011110101110 9
b11111111101111 %
bx000100000000000 <
b100000000000000000 =
b111001100110011 ?
b11001111011111000 ;
1!
#1225000
0!
#1230000
b100001100110011010 $
b0 %
b11010011000010011 ;
b0 ?
b11111010000111001 >
b1000011110101110 @
b100000110011001101 =
1!
#1235000
0!
#1240000
b100010011001100110 $
b11011001000 %
b100001100110011010 =
b110011001101 ?
b11111010000111001 ;
1!
#1245000
0!
#1250000
b100011001100110011 $
b110110010001 %
b11111101100000001 ;
b1100110011010 ?
b100010011001100110 =
1!
#1255000
0!
#1260000
b100100000000000000 $
b1010001011001 %
b100011001100110011 =
b10011001100110 ?
b100000000111001010 ;
1!
#1265000
0!
#1270000
b100100110011001101 $
b1101100100010 %
b100000100010010010 ;
b11001100110011 ?
b100100000000000000 =
1!
#1275000
0!
#1280000
b100101100110011010 $
b10000111101011 %
b100100110011001101 =
b100000000000000 ?
b100000111101011011 ;
1!
#1285000
0!
#1290000
b100110011001100110 $
b10100010110100 %
b100001011000100100 ;
b100110011001101 ?
b100101100110011010 =
1!
#1295000
0!
#1300000
b100111001100110011 $
b10111101111101 %
b100110011001100110 =
b101100110011010 ?
b100001110011101101 ;
1!
#1305000
0!
#1310000
b101000000000000000 $
b11011001000101 %
b100010001110110110 ;
b110011001100110 ?
b100111001100110011 =
1!
#1315000
0!
#1320000
b101000110011001101 $
b101000000000000000 :
b100111101111100111 8
b1000001010001111 9
b11110100001110 %
bx001000000000000 <
b101000000000000000 =
b111001100110011 ?
b100010101001111110 ;
1!
#1325000
0!
#1330000
b101001100110011010 $
b0 %
b100011000101000111 ;
b0 ?
b100111101111100111 >
b1000001010001111 @
b101000110011001101 =
1!
#1335000
0!
#1340000
b101010011001100110 $
b11010000111 %
b101001100110011010 =
b110011001101 ?
b100111101111100111 ;
1!
#1345000
0!
#1350000
b101011001100110011 $
b110100001110 %
b101000001001101110 ;
b1100110011010 ?
b101010011001100110 =
1!
#1355000
0!
#1360000
b101100000000000000 $
b1001110010101 %
b101011001100110011 =
b10011001100110 ?
b101000100011110101 ;
1!
#1365000
0!
#1370000
b101100110011001101 $
b1101000011100 %
b101000111101111100 ;
b11001100110011 ?
b101100000000000000 =
1!
#1375000
0!
#1380000
b101101100110011010 $
b10000010100011 %
b101100110011001101 =
b100000000000000 ?
b101001011000000011 ;
1!
#1385000
0!
