project/hdl/gelu.sv
// GELU Activation — Pipelined SystemVerilog Implementation
// Based on algebraic optimization:
//   GELU(x) = 0.5 * x * (1 + tanh(constant_1*x + constant_2*x^3))
//
// Constants (FP64 hex):
//   constant_1 = sqrt(2/pi)          = 0x3fe9884533d43651
//   constant_2 = constant_1 * 0.044715 = 0x3fa2444f2a4d8b4b
//
// Pipeline (5 slots, 1 cycle each):
//   Slot 1: var_1 = x*x
//           var_2 = constant_2 * x
//           var_3 = constant_1 * x
//           var_4 = x >> 1          (0.5 * x)
//   Slot 2: var_5 = var_1 * var_2   (constant_2 * x^3, since var_1=x^2, var_2=c2*x)
//   Slot 3: var_6 = var_5 + var_3   (constant_1*x + constant_2*x^3)
//   Slot 4: PWL   = tanh_pwl(var_6) (piecewise linear tanh approximation)
//           var_7 = 1 + PWL
//   Slot 5: out   = var_7 * var_4   (0.5 * x * (1 + tanh(...)))
//
// Data format: 32-bit fixed point, Q16.16 (1 sign, 15 integer, 16 fractional)
// Instantiate 16x in parallel for throughput.

module gelu #(
    parameter int DATA_WIDTH = 32,              // total bit width
    parameter int FRAC_BITS  = 16,              // fractional bits (Q16.16)
    parameter int PIPE_DEPTH = 5                // pipeline stages
)(
    input  logic                        clk,
    input  logic                        rst,
    input  logic                        valid_in,
    input  logic signed [DATA_WIDTH-1:0] x,
    output logic                        valid_out,
    output logic signed [DATA_WIDTH-1:0] out
);

    // -------------------------------------------------------------------------
    // Constants in Q16.16 fixed point
    // constant_1 = 0.79788456  -> round(0.79788456 * 2^16) = 52261
    // constant_2 = 0.03567741  -> round(0.03567741 * 2^16) = 2337
    // ONE        = 1.0         -> 1 << 16 = 65536
    // -------------------------------------------------------------------------
    localparam signed [DATA_WIDTH-1:0] CONST_1 = 32'sd52261;
    localparam signed [DATA_WIDTH-1:0] CONST_2 = 32'sd2337;
    localparam signed [DATA_WIDTH-1:0] ONE     = 32'sd65536;  // 1.0 in Q16.16

    // -------------------------------------------------------------------------
    // Pipeline valid shift register
    // -------------------------------------------------------------------------
    logic [PIPE_DEPTH-1:0] valid_pipe;

    always_ff @(posedge clk) begin
        if (rst)
            valid_pipe <= '0;
        else
            valid_pipe <= {valid_pipe[PIPE_DEPTH-2:0], valid_in};
    end

    assign valid_out = valid_pipe[PIPE_DEPTH-1];

    // -------------------------------------------------------------------------
    // Pipeline Slot 1:
    //   var_1 = x * x                (x^2, Q16.16: take upper 32 bits of 64-bit product)
    //   var_2 = constant_2 * x       (c2*x)
    //   var_3 = constant_1 * x       (c1*x)
    //   var_4 = x >>> 1              (0.5*x, arithmetic right shift)
    // -------------------------------------------------------------------------
    logic signed [DATA_WIDTH-1:0] s1_var1, s1_var2, s1_var3, s1_var4;

    always_ff @(posedge clk) begin
        if (rst) begin
            s1_var1 <= '0;
            s1_var2 <= '0;
            s1_var3 <= '0;
            s1_var4 <= '0;
        end else begin
            // Q16.16 * Q16.16 -> Q32.32, take [47:16] for Q16.16 result
            s1_var1 <= (x * x) >>> FRAC_BITS;
            s1_var2 <= (CONST_2 * x) >>> FRAC_BITS;
            s1_var3 <= (CONST_1 * x) >>> FRAC_BITS;
            s1_var4 <= x >>> 1;
        end
    end

    // -------------------------------------------------------------------------
    // Pipeline Slot 2:
    //   var_5 = var_1 * var_2   = x^2 * (c2*x) = c2*x^3
    // -------------------------------------------------------------------------
    logic signed [DATA_WIDTH-1:0] s2_var5;
    logic signed [DATA_WIDTH-1:0] s2_var3, s2_var4;  // forwarded

    always_ff @(posedge clk) begin
        if (rst) begin
            s2_var5 <= '0;
            s2_var3 <= '0;
            s2_var4 <= '0;
        end else begin
            s2_var5 <= (s1_var1 * s1_var2) >>> FRAC_BITS;
            s2_var3 <= s1_var3;
            s2_var4 <= s1_var4;
        end
    end

    // -------------------------------------------------------------------------
    // Pipeline Slot 3:
    //   var_6 = var_5 + var_3   = c2*x^3 + c1*x
    // -------------------------------------------------------------------------
    logic signed [DATA_WIDTH-1:0] s3_var6;
    logic signed [DATA_WIDTH-1:0] s3_var4;  // forwarded

    always_ff @(posedge clk) begin
        if (rst) begin
            s3_var6 <= '0;
            s3_var4 <= '0;
        end else begin
            s3_var6 <= s2_var5 + s2_var3;
            s3_var4 <= s2_var4;
        end
    end

    // -------------------------------------------------------------------------
    // Pipeline Slot 4:
    //   PWL   = tanh_piecewise_linear(var_6)
    //   var_7 = 1 + PWL
    //
    // Piecewise linear tanh approximation (Q16.16):
    //   |x| >= 4.0  -> tanh = sign(x) * 1.0
    //   |x| >= 2.0  -> tanh = sign(x) * (0.9051 + 0.0244*(|x|-2.0))  -- approx
    //   |x| >= 1.0  -> tanh = sign(x) * (0.7616 + 0.1435*(|x|-1.0))  -- approx
    //   |x| <  1.0  -> tanh = x * 0.9  -- linear region approximation
    //
    // All thresholds and slopes in Q16.16
    // -------------------------------------------------------------------------
    localparam signed [DATA_WIDTH-1:0] TANH_SAT   = 32'sd65536;   //  1.0
    localparam signed [DATA_WIDTH-1:0] THRESH_4   = 32'sd262144;  //  4.0
    localparam signed [DATA_WIDTH-1:0] THRESH_2   = 32'sd131072;  //  2.0
    localparam signed [DATA_WIDTH-1:0] THRESH_1   = 32'sd65536;   //  1.0
    localparam signed [DATA_WIDTH-1:0] SLOPE_LIN  = 32'sd58982;   //  0.9  * 2^16
    localparam signed [DATA_WIDTH-1:0] BASE_2     = 32'sd59330;   //  0.9051 * 2^16
    localparam signed [DATA_WIDTH-1:0] SLOPE_2    = 32'sd1600;    //  0.0244 * 2^16
    localparam signed [DATA_WIDTH-1:0] BASE_1     = 32'sd49933;   //  0.7616 * 2^16
    localparam signed [DATA_WIDTH-1:0] SLOPE_1    = 32'sd9408;    //  0.1435 * 2^16

    logic signed [DATA_WIDTH-1:0] s4_pwl, s4_var7;
    logic signed [DATA_WIDTH-1:0] s4_var4;  // forwarded
    logic signed [DATA_WIDTH-1:0] abs_var6;
    logic                         sign_var6;

    always_ff @(posedge clk) begin
        if (rst) begin
            s4_pwl  <= '0;
            s4_var7 <= '0;
            s4_var4 <= '0;
        end else begin
            abs_var6  = (s3_var6 < 0) ? -s3_var6 : s3_var6;
            sign_var6 = s3_var6[DATA_WIDTH-1];

            // Piecewise linear tanh
            if (abs_var6 >= THRESH_4)
                s4_pwl <= sign_var6 ? -TANH_SAT : TANH_SAT;
            else if (abs_var6 >= THRESH_2)
                s4_pwl <= sign_var6 ?
                    -(BASE_2 + ((SLOPE_2 * (abs_var6 - THRESH_2)) >>> FRAC_BITS)) :
                     (BASE_2 + ((SLOPE_2 * (abs_var6 - THRESH_2)) >>> FRAC_BITS));
            else if (abs_var6 >= THRESH_1)
                s4_pwl <= sign_var6 ?
                    -(BASE_1 + ((SLOPE_1 * (abs_var6 - THRESH_1)) >>> FRAC_BITS)) :
                     (BASE_1 + ((SLOPE_1 * (abs_var6 - THRESH_1)) >>> FRAC_BITS));
            else
                s4_pwl <= (SLOPE_LIN * s3_var6) >>> FRAC_BITS;

            s4_var7 <= ONE + s4_pwl;  // 1 + tanh(...)
            s4_var4 <= s3_var4;
        end
    end

    // -------------------------------------------------------------------------
    // Pipeline Slot 5:
    //   output = var_7 * var_4 = (1 + tanh(...)) * (0.5 * x)
    // -------------------------------------------------------------------------
    always_ff @(posedge clk) begin
        if (rst)
            out <= '0;
        else
            out <= (s4_var7 * s4_var4) >>> FRAC_BITS;
    end
    
    
    initial begin
	    $dumpfile("dump.vcd"); // Name of the file to be created
	    $dumpvars(0, gelu);     // 0 means dump all signals in 'mac' and below
    end

endmodule

project/hdl/result/preliminary.vcd
$date
	Sun Apr 26 22:09:43 2026
$end
$version
	Icarus Verilog
$end
$timescale
	1ps
$end
$scope module gelu $end
$var wire 1 ! clk $end
$var wire 1 " rst $end
$var wire 1 # valid_in $end
$var wire 32 $ x [31:0] $end
$var wire 1 % valid_out $end
$var parameter 32 & BASE_1 $end
$var parameter 32 ' BASE_2 $end
$var parameter 32 ( CONST_1 $end
$var parameter 32 ) CONST_2 $end
$var parameter 32 * DATA_WIDTH $end
$var parameter 32 + FRAC_BITS $end
$var parameter 32 , ONE $end
$var parameter 32 - PIPE_DEPTH $end
$var parameter 32 . SLOPE_1 $end
$var parameter 32 / SLOPE_2 $end
$var parameter 32 0 SLOPE_LIN $end
$var parameter 32 1 TANH_SAT $end
$var parameter 32 2 THRESH_1 $end
$var parameter 32 3 THRESH_2 $end
$var parameter 32 4 THRESH_4 $end
$var reg 32 5 abs_var6 [31:0] $end
$var reg 32 6 out [31:0] $end
$var reg 32 7 s1_var1 [31:0] $end
$var reg 32 8 s1_var2 [31:0] $end
$var reg 32 9 s1_var3 [31:0] $end
$var reg 32 : s1_var4 [31:0] $end
$var reg 32 ; s2_var3 [31:0] $end
$var reg 32 < s2_var4 [31:0] $end
$var reg 32 = s2_var5 [31:0] $end
$var reg 32 > s3_var4 [31:0] $end
$var reg 32 ? s3_var6 [31:0] $end
$var reg 32 @ s4_pwl [31:0] $end
$var reg 32 A s4_var4 [31:0] $end
$var reg 32 B s4_var7 [31:0] $end
$var reg 1 C sign_var6 $end
$var reg 5 D valid_pipe [4:0] $end
$upscope $end
$enddefinitions $end
$comment Show the parameter values. $end
$dumpall
b1000000000000000000 4
b100000000000000000 3
b10000000000000000 2
b10000000000000000 1
b1110011001100110 0
b11001000000 /
b10010011000000 .
b101 -
b10000000000000000 ,
b10000 +
b100000 *
b100100100001 )
b1100110000100101 (
b1110011111000010 '
b1100001100001101 &
$end
#0
$dumpvars
b0 D
xC
b0 B
b0 A
b0 @
b0 ?
b0 >
b0 =
b0 <
b0 ;
b0 :
b0 9
b0 8
b0 7
b0 6
bx 5
0%
b0 $
0#
1"
1!
$end
#5000
0!
#10000
1#
0"
1!
#15000
0!
#20000
b1 D
b10000000000000000 B
0C
b0 5
1!
#25000
0!
#30000
b11 D
1!
#35000
0!
#40000
b111 D
1!
#45000
0!
#50000
b1111 D
1!
#55000
0!
#60000
0#
1%
b11111 D
1!
#65000
0!
#70000
b10000000000000000 $
1#
b11110 D
1!
#75000
0!
#80000
b11101 D
b1000000000000000 :
b11111111111111111100110000100101 9
b100100100001 8
1!
#85000
0!
#90000
b1000000000000000 <
b11111111111111111100110000100101 ;
b11011 D
1!
#95000
0!
#100000
b10111 D
b1000000000000000 >
b11111111111111111100110000100101 ?
1!
#105000
0!
#110000
0%
b1000000000000000 A
b11111111111111111101000101010100 @
b1111 D
1C
b11001111011011 5
1!
#115000
0!
#120000
0#
1%
b11111 D
b1101000101010100 B
b11111111111111111000000000000000 6
1!
#125000
0!
#130000
b110100010101010 6
b11110 D
1!
#130001
b0 $
1"
#135001
0!
#140001
0%
b0 D
b0 :
b0 9
b0 8
b0 <
b0 ;
b0 >
b0 ?
b0 A
b0 B
b0 @
b0 6
1!
#145001
0!
#150001
b1010000000000000000 $
1#
0"
1!
#155001
0!
#160001
b1 D
b101000000000000000 :
b11111111111111111111110010111001 9
b10110110100101 8
b10000000000000000 B
0C
b0 5
1!
#165001
0!
#170001
b101000000000000000 <
b11111111111111111111110010111001 ;
b11 D
1!
#175001
0!
#180001
b111 D
b101000000000000000 >
b11111111111111111111110010111001 ?
1!
#185001
0!
#190001
b101000000000000000 A
b11111111111111111111110100001100 @
b1111 D
1C
b1101000111 5
1!
#195001
0!
#200001
0#
1%
b11111 D
b1111110100001100 B
b11111111111111111000000000000000 6
1!
#205001
0!
#210001
b111100010011110 6
b11110 D
1!
#210002
b0 $
1"
#215002
0!
#220002
0%
b0 D
b0 :
b0 9
b0 8
b0 <
b0 ;
b0 >
b0 ?
b0 A
b0 B
b0 @
b0 6
1!
#225002
0!
#230002
b10000000000000000 $
1#
0"
1!
#235002
0!
#240002
0#
b1 D
b1000000000000000 :
b11111111111111111100110000100101 9
b100100100001 8
b10000000000000000 B
0C
b0 5
1!
#245002
0!
#250002
b1000000000000000 <
b11111111111111111100110000100101 ;
b10 D
1!
#255002
0!
#260002
b100 D
b1000000000000000 >
b11111111111111111100110000100101 ?
1!
#265002
0!
#270002
b1000000000000000 A
b11111111111111111101000101010100 @
b1000 D
1C
b11001111011011 5
1!
#275002
0!
#280002
1%
b10000 D
b1101000101010100 B
b11111111111111111000000000000000 6
1!
#285002
0!
#290002
0%
b110100010101010 6
b0 D
1!
#290003
b0 $
1"
#295003
0!
#300003
b0 :
b0 9
b0 8
b0 <
b0 ;
b0 >
b0 ?
b0 A
b0 B
b0 @
b0 6
1!
#305003
0!
#310003
1#
0"
1!
#315003
0!
#320003
b1 D
b10000000000000000 B
0C
b0 5
1!
#325003
0!
#330003
b11 D
1!
#335003
0!
#340003
b111 D
1!
#345003
0!
#350003
b1111 D
1!
#355003
0!
#360003
0#
1%
b11111 D
1!
#365003
0!
#370003
b11110 D
1!
#370004
1"
#375004
0!
#380004
0%
b0 D
b0 B
1!
#385004
0!
#390004
b1000000000000000 $
1#
0"
1!
#395004
0!
#400004
b10000000000000000 $
b1 D
b100000000000000 :
b110011000010010 9
b10010010000 8
b100000000000000 7
b10000000000000000 B
1!
#405004
0!
#410004
b11000000000000000 $
b100000000000000 <
b110011000010010 ;
b100100100 =
b1000000000000000 :
b11111111111111111100110000100101 9
b100100100001 8
b0 7
b11 D
1!
#415004
0!
#420004
b100000000000000000 $
b111 D
b1100000000000000 :
b11001000110111 9
b110110110001 8
b100000000000000 7
b1000000000000000 <
b11111111111111111100110000100101 ;
b0 =
b100000000000000 >
b110011100110110 ?
1!
#425004
0!
#430004
b11111111111111111000000000000000 $
b100000000000000 A
b101110011100011 @
b1000000000000000 >
b11111111111111111100110000100101 ?
b1100000000000000 <
b11001000110111 ;
b1101101100 =
b10000000000000000 :
b11111111111111111001100001001010 9
b1001001000010 8
b0 7
b1111 D
b110011100110110 5
1!
#435004
0!
#440004
b11111111111111110000000000000000 $
1%
b11111 D
b11111111111111111100000000000000 :
b11111111111111111001100111101101 9
b11111111111111111111101101101111 8
b100000000000000 7
b10000000000000000 <
b11111111111111111001100001001010 ;
b0 =
b1100000000000000 >
b11010110100011 ?
b1000000000000000 A
b10101110011100011 B
b11111111111111111101000101010100 @
b100000000000000 6
1C
b11001111011011 5
1!
#445004
0!
#450004
b11111111111111101000000000000000 $
b11111111111111111010111001110001 6
b1100000000000000 A
b1101000101010100 B
b11000001000101 @
b10000000000000000 >
b11111111111111111001100001001010 ?
b11111111111111111100000000000000 <
b11111111111111111001100111101101 ;
b11111111111111111111111011011011 =
b11111111111111111000000000000000 :
b11001111011011 9
b11111111111111111111011011011111 8
b0 7
0C
b11010110100011 5
1!
#455004
0!
#460004
b11111111111111100000000000000000 $
b11111111111111110100000000000000 :
b11111111111111111100110111001000 9
b11111111111111111111001001001110 8
b100000000000000 7
b11111111111111111000000000000000 <
b11001111011011 ;
b0 =
b11111111111111111100000000000000 >
b11111111111111111001100011001000 ?
b10000000000000000 A
b10011000001000101 B
b11111111111111111010001010101001 @
b11111111111111111001110011111111 6
1C
b110011110110110 5
1!
#465004
0!
#470004
0#
b11000001000101 6
b11111111111111111100000000000000 A
b1010001010101001 B
b11111111111111111010001100011010 @
b11111111111111111000000000000000 >
b11001111011011 ?
b11111111111111110100000000000000 <
b11111111111111111100110111001000 ;
b11111111111111111111110010010011 =
b11111111111111110000000000000000 :
b110011110110110 9
b11111111111111111110110110111110 8
b0 7
b110011100111000 5
1!
#475004
0!
#480004
b11110 D
b11111111111111110000000000000000 <
b110011110110110 ;
b0 =
b11111111111111110100000000000000 >
b11111111111111111100101001011011 ?
b11111111111111111000000000000000 A
b1010001100011010 B
b10111010101011 @
b11111111111111111101011101010101 6
0C
b11001111011011 5
1!
#485004
0!
#490004
b11111111111111111010111001110011 6
b11111111111111110100000000000000 A
b10010111010101011 B
b11111111111111111100111110111000 @
b11111111111111110000000000000000 >
b110011110110110 ?
b11100 D
1C
b11010110100101 5
1!
#495004
0!
#500004
b11000 D
b11111111111111110000000000000000 A
b1100111110111000 B
b101110101010110 @
b1110011111111 6
0C
b110011110110110 5
1!
#505004
0!
#510004
b11000001001000 6
b10101110101010110 B
b10000 D
1!
#515004
0!
#520004
0%
b0 D
b11111111111111111010001010101010 6
1!
