codefest/cf04/cocotb_mac/mac_correct.sv
module mac (
    input  logic        clk,
    input  logic        rst,
    input  logic signed [7:0]  a,
    input  logic signed [7:0]  b,
    output logic signed [31:0] out
);

    logic signed [15:0] product;

    always_ff @(posedge clk) begin
        if (rst) begin
            out <= 32'sd0;
        end else begin
            product = a * b;
            out <= out + 32'(product);
        end
    end
    // Add this for VCD generation
initial begin
    $dumpfile("dump.vcd"); // Name of the file to be created
    $dumpvars(0, mac);     // 0 means dump all signals in 'mac' and below
end

endmodule

codefest/cf04/cocotb_mac/test_mac_all.vcd
$date
	Sun Apr 26 21:46:54 2026
$end
$version
	Icarus Verilog
$end
$timescale
	1ps
$end
$scope module mac $end
$var wire 8 ! a [7:0] $end
$var wire 8 " b [7:0] $end
$var wire 1 # clk $end
$var wire 1 $ rst $end
$var reg 32 % out [31:0] $end
$var reg 16 & product [15:0] $end
$upscope $end
$enddefinitions $end
$comment Show the parameter values. $end
$dumpall
$end
#0
$dumpvars
bx &
b0 %
0$
1#
b100 "
b11 !
$end
#5000
0#
#10000
b1100 %
b1100 &
1#
#15000
0#
#20000
b11000 %
1#
#25000
0#
#30000
b100100 %
1#
#30001
1$
#35000
0#
#40000
b0 %
1#
#45002
0#
#50002
b1111111111111111111111111111000 %
0$
1#
#55002
0#
#60002
b10000000000000000000000000000100 %
1#
